Workbook

Sheet Extraction
A1: Collaborateur | B1: 1 | C1: 11C | D1: 11N | E1: 11NC | F1: 11S | G1: 12C | H1: 12S | I1: 13 | J1: 13B | K1: 13C | L1: 13D | M1: 14B | N1: 14D | O1: 16 | P1: 16A | Q1: 16N | R1: 17 | S1: 17E | T1: 18E | U1: 18I | V1: 19 | W1: 1BBR-B | X1: 2 | Y1: 21 | Z1: 24 | AA1: 27 | AB1: 29 | AC1: 2BBR | AD1: 4 | AE1: 41N | AF1: 42N | AG1: 43N | AH1: 44 | AI1: 45 | AJ1: 46C | AK1: 46F | AL1: 46N | AM1: 47 | AN1: 47E | AO1: 49 | AP1: 5 | AQ1: 51 | AR1: 52 | AS1: 53 | AT1: 54 | AU1: 55 | AV1: 55A | AW1: 55E | AX1: 55F | AY1: 56 | AZ1: 5I | BA1: 6 | BB1: 60 | BC1: 61 | BD1: 62 | BE1: 63 | BF1: 64 | BG1: 64A | BH1: 65A | BI1: 65B | BJ1: 67 | BK1: 68 | BL1: 69 | BM1: 69P | BN1: 6DI | BO1: 6I | BP1: 71 | BQ1: 72 | BR1: 72CH | BS1: 72I | BT1: 73 | BU1: 73F | BV1: 74 | BW1: 75 | BX1: 76 | BY1: 76A | BZ1: 76B | CA1: 77 | CB1: 78 | CC1: 79 | CD1: 7I | CE1: A | CF1: A1 | CG1: A13CAL | CH1: A13RA | CI1: A14 | CJ1: A16A | CK1: A16ARA | CL1: A1CAL | CM1: A1RA | CN1: A7CAL | CO1: A7RA | CP1: A7S | CQ1: B1 | CR1: C | CS1: C1 | CT1: C13 | CU1: C7 | CV1: C73 | CW1: CCA24 | CX1: F | CY1: F1 | CZ1: F13 | DA1: F13A | DB1: F13B | DC1: F13CO | DD1: F13FSA | DE1: F14A | DF1: F1B | DG1: F1CO | DH1: F1FSA | DI1: F1VG | DJ1: F4VG | DK1: F7 | DL1: F7A | DM1: F7CO | DN1: F7VG | DO1: I | DP1: M | DQ1: P | DR1: P1 | DS1: P1A | DT1: P1EP | DU1: P1R | DV1: P1VF | DW1: P4 | DX1: P4EP | DY1: P4SD | DZ1: P4VF | EA1: P51 | EB1: P5BV | EC1: P5EP | ED1: P5P | EE1: P5T | EF1: P6A | EG1: P6BT | EH1: P6BV | EI1: P6P | EJ1: P6T | EK1: P6Z | EL1: P72A | EM1: P7C | EN1: P7COM | EO1: P7P | EP1: P7R | EQ1: P7VF | ER1: V | ES1: V1 | ET1: V4G | EU1: Z | EV1: Total
A2: Anderfuhren Sandrine | W2: 3.75 | AM2: 1.25 | AQ2: 50 | AR2: 20.5 | AS2: 1.75 | BC2: 16.25 | BE2: 1.5 | BF2: 9.75 | BG2: 1.5 | BL2: 5.75 | BM2: 10.5 | BQ2: 1.25 | BT2: 10.51 | BU2: 139 | CB2: 1.5 | CC2: 4.25 | CX2: 7.2 | DM2: 2 | EV2: 288.21
A3: Baratti Graziano | I3: 1.75 | M3: 0.25 | N3: 0.5 | O3: 0.25 | AO3: 9 | AQ3: 41.75 | AR3: 4.75 | AS3: 10.5 | AT3: 4 | AU3: 1.75 | AY3: 0.75 | BA3: 103.5 | BB3: 1.25 | BC3: 700.75 | BD3: 2.75 | BE3: 27.75 | BF3: 106.5 | BG3: 15.5 | BK3: 49.25 | BL3: 55.25 | BO3: 4.5 | BP3: 10.25 | BQ3: 15.25 | BT3: 14.25 | BX3: 4.5 | BY3: 15.25 | BZ3: 1.25 | CA3: 9 | CB3: 37 | CC3: 59.5 | CD3: 0.75 | CN3: 1.25 | CR3: 8 | CX3: 57.6 | DM3: 0.5 | DN3: 2 | DP3: 32.5 | DQ3: 55.5 | EQ3: 2.75 | ER3: 197.5 | EU3: 3 | EV3: 1669.85
A4: Bolay Valérie | B4: 104.5 | C4: 13 | D4: 49 | E4: 10.5 | F4: 121.75 | H4: 311.25 | O4: 1.75 | P4: 1 | Q4: 4 | V4: 5.5 | Y4: 5 | AA4: 9.5 | BK4: 0.25 | BP4: 19 | BT4: 6.25 | BY4: 2.25 | CB4: 28.5 | CC4: 31.5 | CE4: 122 | CJ4: 18.25 | CK4: 6.25 | CM4: 3.5 | CQ4: 7.75 | CR4: 4 | CS4: 0.75 | CX4: 49.6 | DI4: 4.75 | DP4: 29 | DQ4: 36 | DR4: 2.5 | DS4: 111.25 | DT4: 104 | DU4: 30.75 | DV4: 4 | ER4: 142.5 | ES4: 8.75 | EV4: 1410.1
A5: Castello Donja | F5: 31.5 | H5: 119.25 | BP5: 2.25 | CB5: 1 | CC5: 16 | CX5: 4 | DP5: 32 | DQ5: 7 | ER5: 36 | EU5: 4 | EV5: 253
A6: Chatelain Antonin | AD6: 21.25 | AE6: 234.5 | AF6: 442 | AH6: 23.5 | AI6: 0.5 | AJ6: 3 | AO6: 0.25 | BP6: 0.5 | BQ6: 7.13 | BY6: 24 | CA6: 1.5 | CB6: 38.25 | CC6: 29.75 | CR6: 37 | CX6: 41.6 | DQ6: 42.5 | ER6: 90.5 | EU6: 30 | EV6: 1067.73
A7: Chatenoux Didier | AD7: 27 | AE7: 387.75 | AF7: 353.5 | AG7: 268 | AI7: 3 | AJ7: 2 | AL7: 7.5 | AM7: 2.75 | AN7: 2 | AO7: 50.5 | BP7: 45 | BX7: 5.63 | CB7: 43.75 | CC7: 0.25 | CR7: 12 | CX7: 50.4 | DP7: 16 | DQ7: 53 | ER7: 131.5 | EV7: 1461.53
A8: Cosandey Philippe | EV8: 0
A9: Dos Santos Martins Carlos | AP9: 19 | AQ9: 414 | AR9: 155 | AS9: 53.75 | AT9: 50.5 | AU9: 138.5 | AX9: 12.25 | AY9: 8.25 | BQ9: 3 | BT9: 4.5 | BU9: 15.5 | CB9: 23.5 | CC9: 1.5 | CR9: 19.5 | CX9: 36 | DM9: 3 | DQ9: 14.25 | ER9: 70 | EU9: 7 | EV9: 1049
A10: Favre Corinne | B10: 294.25 | G10: 1.25 | H10: 171 | I10: 2 | J10: 0.25 | M10: 37.75 | N10: 0.5 | O10: 1.5 | P10: 19.75 | R10: 2.5 | S10: 2 | T10: 0.5 | U10: 2.5 | V10: 100.5 | X10: 16.25 | Y10: 11 | AA10: 0.75 | BP10: 18.5 | BT10: 3.75 | BW10: 0.5 | BX10: 11.51 | CA10: 32.5 | CB10: 80.25 | CC10: 73 | CF10: 1.25 | CJ10: 13 | CK10: 10.75 | CO10: 2.5 | CQ10: 2.75 | CR10: 49.75 | CS10: 5.75 | CU10: 0.5 | CW10: 5.75 | CX10: 43.2 | DK10: 1.75 | DL10: 1 | DN10: 1.75 | DP10: 15.5 | DQ10: 43.75 | DR10: 1 | DS10: 8.75 | DT10: 10.25 | DU10: 12 | EQ10: 0.5 | ER10: 128.5 | EV10: 1244.21
A11: Fleuret Thi Hanh | B11: 37.5 | I11: 12 | J11: 11 | L11: 0.25 | AC11: 1.25 | AD11: 0.25 | AO11: 4.75 | AS11: 1.5 | AT11: 1 | AU11: 0.5 | BA11: 1 | BC11: 183.5 | BE11: 0.25 | BF11: 305.75 | BH11: 278 | BK11: 80.5 | BL11: 47.5 | BM11: 15.5 | BO11: 5.75 | BQ11: 21.5 | BT11: 52.63 | BX11: 1.75 | BY11: 2.5 | BZ11: 0.25 | CB11: 14.5 | CC11: 67.25 | CH11: 4 | CR11: 8 | CX11: 50.4 | CY11: 1.5 | CZ11: 2.25 | DA11: 2.75 | DJ11: 1 | DN11: 5.25 | DO11: 10.75 | DP11: 12 | DQ11: 52.25 | DV11: 1 | DZ11: 0.5 | EA11: 2.25 | EG11: 10.75 | EQ11: 8 | ER11: 144 | EV11: 1464.78
A12: Galley Laurent | AI12: 0.75 | AO12: 3.75 | AP12: 33.5 | AQ12: 393.75 | AR12: 84.5 | AS12: 107 | AT12: 50.5 | AU12: 27.5 | AV12: 0.75 | AX12: 3.5 | AY12: 28.5 | AZ12: 1.25 | BE12: 0.5 | BQ12: 3.5 | BT12: 2.25 | BV12: 0.75 | BX12: 2 | BY12: 1.75 | CB12: 22 | CC12: 29 | CX12: 36 | DM12: 0.75 | DP12: 121 | DQ12: 8.25 | ER12: 80 | EV12: 1043
A13: Geuggis Gilles | AD13: 16.5 | AE13: 52.75 | AF13: 218.75 | AH13: 35.25 | AI13: 4 | AM13: 2 | AO13: 6.75 | BP13: 12 | BX13: 5.63 | CA13: 8.25 | CB13: 7.5 | CC13: 12.5 | CR13: 12.5 | CV13: 3.5 | CX13: 14.4 | DQ13: 1 | ER13: 10 | EV13: 423.28
A14: Harth Eric | AD14: 152.5 | AJ14: 3.75 | AM14: 8 | AO14: 0.25 | BP14: 2 | CA14: 56.75 | CB14: 47.5 | CC14: 2 | CE14: 64 | CX14: 20 | DP14: 16 | DQ14: 17.25 | DT14: 3 | DW14: 1.25 | DX14: 26.75 | DY14: 0.5 | EB14: 2.75 | EE14: 190.25 | ER14: 76 | EV14: 690.5
A15: Holenweg Pascale | B15: 10.5 | D15: 28 | F15: 251.25 | H15: 304 | P15: 33 | R15: 57 | V15: 38.5 | BP15: 9.5 | BW15: 29.25 | CB15: 9.25 | CC15: 47.25 | CQ15: 14.5 | CR15: 12 | CX15: 39.6 | DI15: 1 | DP15: 20 | DQ15: 23.75 | DS15: 5.25 | DT15: 15.75 | DV15: 50 | ER15: 144 | EV15: 1143.35
A16: Kuhn Christian | AD16: 51.5 | AE16: 79.5 | AF16: 154 | AH16: 29.75 | AI16: 3 | AJ16: 1.75 | AL16: 2.5 | AO16: 48.63 | BP16: 2 | BY16: 27.5 | CA16: 0.75 | CB16: 16 | CC16: 15.25 | CX16: 39.2 | DP16: 279.75 | DQ16: 7.75 | DW16: 0.75 | ER16: 114 | EU16: 228.75 | EV16: 1102.33
A17: Leon Gabriel | EV17: 0
A18: Merzouk Séverine | B18: 28.5 | C18: 13.25 | D18: 79 | E18: 9.25 | F18: 99 | G18: 7.75 | H18: 284 | P18: 88.75 | Q18: 6 | R18: 9 | S18: 13.25 | V18: 15.75 | BP18: 10.5 | BT18: 40 | CB18: 12.5 | CC18: 35 | CF18: 0.25 | CR18: 12 | CS18: 0.75 | CX18: 36 | CY18: 2.75 | DI18: 8.75 | DP18: 43.75 | DQ18: 41.5 | DR18: 9.75 | DT18: 18.25 | DV18: 15 | ER18: 104.5 | EU18: 4 | EV18: 1048.75
A19: Meyrat Jean-Marc | B19: 3.75 | X19: 117.5 | Y19: 108.25 | Z19: 125 | AA19: 14.25 | AB19: 4.75 | AE19: 16.25 | AP19: 486 | AX19: 5 | AZ19: 5.5 | BE19: 2.5 | BG19: 80 | BM19: 7.75 | BQ19: 4.75 | BT19: 94.38 | BU19: 43.75 | BV19: 15.25 | BW19: 11.25 | CA19: 20 | CB19: 137 | CC19: 13.5 | CR19: 29.5 | CX19: 57.6 | DP19: 46.5 | DQ19: 4.5 | EA19: 1.5 | EG19: 15 | EL19: 9.5 | EN19: 28 | ER19: 167 | EV19: 1675.48
A20: Othenin Roberto | AD20: 3.5 | AE20: 22.75 | AF20: 176 | AM20: 0.25 | AO20: 10 | BP20: 4 | BY20: 1.25 | CB20: 1 | CX20: 5.6 | DQ20: 4.75 | EV20: 229.1
A21: Paul Bertram | B21: 7.5 | G21: 0.75 | I21: 20 | J21: 70 | K21: 14.75 | L21: 3.25 | O21: 10 | AB21: 26.25 | AD21: 0.75 | AO21: 1.5 | AQ21: 6.5 | AR21: 0.5 | BA21: 7 | BC21: 17.75 | BE21: 14.25 | BF21: 0.25 | BG21: 74 | BH21: 2.75 | BI21: 49.75 | BK21: 58 | BL21: 182.25 | BM21: 15 | BO21: 23.5 | BQ21: 7.5 | BR21: 0.25 | BS21: 8.25 | BX21: 3 | BY21: 3.5 | BZ21: 0.25 | CB21: 11.5 | CC21: 60.75 | CG21: 2.75 | CL21: 2.25 | CR21: 8 | CT21: 3.5 | CX21: 36 | DC21: 28.5 | DD21: 2 | DG21: 15 | DH21: 1.5 | DM21: 1 | DN21: 0.75 | DQ21: 45.5 | DS21: 1 | EA21: 7 | EB21: 2 | EC21: 8.75 | EE21: 9.75 | EH21: 1.5 | EI21: 0.75 | EJ21: 7.25 | EM21: 1.25 | EQ21: 2.5 | ER21: 140 | ET21: 0.75 | EU21: 20 | EV21: 1050.5
A22: Pillet Anne | B22: 23.5 | I22: 1 | O22: 3.5 | P22: 1 | Y22: 2 | AD22: 20.5 | AO22: 17 | AP22: 32 | AQ22: 2.25 | AS22: 0.5 | AU22: 5.25 | AW22: 2.75 | AX22: 10 | BA22: 11.25 | BD22: 1.5 | BE22: 2 | BK22: 0.5 | BP22: 6.75 | BQ22: 41.75 | BR22: 6.25 | BS22: 1 | BT22: 1.75 | BV22: 27 | BX22: 7.25 | BY22: 2.75 | CA22: 169.75 | CB22: 426.5 | CC22: 55.25 | CE22: 219.5 | CP22: 0.5 | CR22: 8 | CX22: 57.6 | DG22: 0.5 | DL22: 1.5 | DM22: 0.25 | DP22: 226.5 | DQ22: 46.5 | DS22: 1 | DU22: 1.75 | ED22: 6.5 | EE22: 36.75 | EF22: 39 | EJ22: 48 | EO22: 35.5 | EP22: 1 | ER22: 252 | EU22: 4 | EV22: 1868.85
A23: Rérat Cédric | I23: 12.75 | V23: 0.5 | AO23: 33.25 | AQ23: 0.5 | AT23: 1 | AU23: 2.25 | AX23: 0.5 | BA23: 69.25 | BB23: 39 | BC23: 396.75 | BD23: 33.75 | BE23: 70.75 | BF23: 191 | BG23: 99.5 | BJ23: 0.75 | BK23: 14.75 | BL23: 38.5 | BM23: 0.75 | BN23: 0.5 | BO23: 1 | BP23: 4.75 | BQ23: 7.75 | BT23: 13.25 | BX23: 9.51 | BY23: 3.5 | CA23: 74.75 | CB23: 293.25 | CC23: 238.5 | CN23: 1 | CR23: 46 | CX23: 72 | DK23: 1.75 | DM23: 3.75 | DN23: 5 | DP23: 8 | DQ23: 0.75 | EF23: 109.75 | EJ23: 1.25 | EK23: 4.25 | EQ23: 4.25 | ER23: 176 | ES23: 1 | EV23: 2087.01
A24: Rossier Christophe | AD24: 54.75 | AE24: 261 | AF24: 411.5 | AH24: 64 | AI24: 13.5 | AJ24: 9.5 | AK24: 3 | AL24: 7.25 | AM24: 28.5 | AO24: 30.75 | BP24: 63.5 | BX24: 7.13 | BY24: 17 | CA24: 9 | CB24: 78.25 | CC24: 21.25 | CR24: 12 | CV24: 1.5 | CX24: 48 | DI24: 6.5 | DJ24: 7.5 | DP24: 24 | DQ24: 56.25 | DV24: 11 | DW24: 27.75 | DZ24: 18.5 | ER24: 128 | EV24: 1420.88
A25: Vukanovic Natasha | EV25: 0
A26: Walter Gamila | EV26: 0
A27: Boulsa Bénévolat | DB27: 0.75 | DF27: 3.75 | EV27: 4.5
A28: CIR Bibliothécaire | EV28: 0
A29: Etudiant Temporaire | EV29: 0
A30: Klappenbach Sacsahuaman | M30: 125.5 | N30: 8.5 | AY30: 88 | CI30: 2.5 | DE30: 2.5 | EV30: 227
A31: reliure bénévoles | BE31: 28.5 | DM31: 14.25 | EV31: 42.75
A32: Tempo Audio | EV32: 0
A33: Tempo Braille | EV33: 0
A34: Total | B34: 510 | C34: 26.25 | D34: 156 | E34: 19.75 | F34: 503.5 | G34: 9.75 | H34: 1189.5 | I34: 49.5 | J34: 81.25 | K34: 14.75 | L34: 3.5 | M34: 163.5 | N34: 9.5 | O34: 17 | P34: 143.5 | Q34: 10 | R34: 68.5 | S34: 15.25 | T34: 0.5 | U34: 2.5 | V34: 160.75 | W34: 3.75 | X34: 133.75 | Y34: 126.25 | Z34: 125 | AA34: 24.5 | AB34: 31 | AC34: 1.25 | AD34: 348.5 | AE34: 1054.5 | AF34: 1755.75 | AG34: 268 | AH34: 152.5 | AI34: 24.75 | AJ34: 20 | AK34: 3 | AL34: 17.25 | AM34: 42.75 | AN34: 2 | AO34: 216.38 | AP34: 570.5 | AQ34: 908.75 | AR34: 265.25 | AS34: 175 | AT34: 107 | AU34: 175.75 | AV34: 0.75 | AW34: 2.75 | AX34: 31.25 | AY34: 125.5 | AZ34: 6.75 | BA34: 192 | BB34: 40.25 | BC34: 1315 | BD34: 38 | BE34: 148 | BF34: 613.25 | BG34: 270.5 | BH34: 280.75 | BI34: 49.75 | BJ34: 0.75 | BK34: 203.25 | BL34: 329.25 | BM34: 49.5 | BN34: 0.5 | BO34: 34.75 | BP34: 210.5 | BQ34: 113.38 | BR34: 6.5 | BS34: 9.25 | BT34: 243.52 | BU34: 198.25 | BV34: 43 | BW34: 41 | BX34: 57.91 | BY34: 101.25 | BZ34: 1.75 | CA34: 382.25 | CB34: 1330.5 | CC34: 813.25 | CD34: 0.75 | CE34: 405.5 | CF34: 1.5 | CG34: 2.75 | CH34: 4 | CI34: 2.5 | CJ34: 31.25 | CK34: 17 | CL34: 2.25 | CM34: 3.5 | CN34: 2.25 | CO34: 2.5 | CP34: 0.5 | CQ34: 25 | CR34: 278.25 | CS34: 7.25 | CT34: 3.5 | CU34: 0.5 | CV34: 5 | CW34: 5.75 | CX34: 802 | CY34: 4.25 | CZ34: 2.25 | DA34: 2.75 | DB34: 0.75 | DC34: 28.5 | DD34: 2 | DE34: 2.5 | DF34: 3.75 | DG34: 15.5 | DH34: 1.5 | DI34: 21 | DJ34: 8.5 | DK34: 3.5 | DL34: 2.5 | DM34: 25.5 | DN34: 14.75 | DO34: 10.75 | DP34: 922.5 | DQ34: 562 | DR34: 13.25 | DS34: 127.25 | DT34: 151.25 | DU34: 44.5 | DV34: 81 | DW34: 29.75 | DX34: 26.75 | DY34: 0.5 | DZ34: 19 | EA34: 10.75 | EB34: 4.75 | EC34: 8.75 | ED34: 6.5 | EE34: 236.75 | EF34: 148.75 | EG34: 25.75 | EH34: 1.5 | EI34: 0.75 | EJ34: 56.5 | EK34: 4.25 | EL34: 9.5 | EM34: 1.25 | EN34: 28 | EO34: 35.5 | EP34: 1 | EQ34: 18 | ER34: 2332 | ES34: 9.75 | ET34: 0.75 | EU34: 300.75 | EV34: 23965.69

Sheet Heures épurées
A1: Collaborateur | B1: 1 | C1: 11C | D1: 11N | E1: 11NC | F1: 11S | G1: 12C | H1: 12S | I1: 13 | J1: 13B | K1: 13C | L1: 13D | M1: 14B | N1: 14D | O1: 16 | P1: 16A | Q1: 16N | R1: 17 | S1: 17E | T1: 18E | U1: 18I | V1: 19 | W1: 1BBR-B | X1: 2 | Y1: 21 | Z1: 24 | AA1: 27 | AB1: 29 | AC1: 2BBR | AD1: 4 | AE1: 41N | AF1: 42N | AG1: 43N | AH1: 44 | AI1: 45 | AJ1: 46C | AK1: 46F | AL1: 46N | AM1: 47 | AN1: 47E | AO1: 49 | AP1: 5 | AQ1: 51 | AR1: 52 | AS1: 53 | AT1: 54 | AU1: 55 | AV1: 55A | AW1: 55E | AX1: 55F | AY1: 56 | AZ1: 5I | BA1: 6 | BB1: 60 | BC1: 61 | BD1: 62 | BE1: 63 | BF1: 64 | BG1: 64A | BH1: 65A | BI1: 65B | BJ1: 67 | BK1: 68 | BL1: 69 | BM1: 69P | BN1: 6DI | BO1: 6I | BP1: 71 | BQ1: 72 | BR1: 72CH | BS1: 72I | BT1: 73 | BU1: 73F | BV1: 74 | BW1: 75 | BX1: 76 | BY1: 76A | BZ1: 76B | CA1: 77 | CB1: 78 | CC1: 79 | CD1: 7I | CE1: A | CF1: A1 | CG1: A13CAL | CH1: A13RA | CI1: A14 | CJ1: A16A | CK1: A16ARA | CL1: A1CAL | CM1: A1RA | CN1: A7CAL | CO1: A7RA | CP1: A7S | CQ1: B1 | CR1: C | CS1: C1 | CT1: C13 | CU1: C7 | CV1: C73 | CW1: CCA24 | CX1: F | CY1: F1 | CZ1: F13 | DA1: F13A | DB1: F13B | DC1: F13CO | DD1: F13FSA | DE1: F14A | DF1: F1B | DG1: F1CO | DH1: F1FSA | DI1: F1VG | DJ1: F4VG | DK1: F7 | DL1: F7A | DM1: F7CO | DN1: F7VG | DO1: I | DP1: M | DQ1: P | DR1: P1 | DS1: P1A | DT1: P1EP | DU1: P1R | DV1: P1VF | DW1: P4 | DX1: P4EP | DY1: P4SD | DZ1: P4VF | EA1: P51 | EB1: P5BV | EC1: P5EP | ED1: P5P | EE1: P5T | EF1: P6A | EG1: P6BT | EH1: P6BV | EI1: P6P | EJ1: P6T | EK1: P6Z | EL1: P72A | EM1: P7C | EN1: P7COM | EO1: P7P | EP1: P7R | EQ1: P7VF | ER1: V | ES1: V1 | ET1: V4G | EU1: Z | EV1: Total
A2: Anderfuhren Sandrine | W2: 3.75 | AM2: 1.25 | AQ2: 50 | AR2: 20.5 | AS2: 1.75 | BC2: 16.25 | BE2: 1.5 | BF2: 9.75 | BG2: 1.5 | BL2: 5.75 | BM2: 10.5 | BQ2: 1.25 | BT2: 10.51 | BU2: 139 | CB2: 1.5 | CC2: 4.25 | CX2: 7.2 | DM2: 2 | EV2: =SUM(B2:EU2) -> 288.21
A3: Baratti Graziano | I3: 1.75 | M3: 0.25 | N3: 0.5 | O3: 0.25 | AO3: 9 | AQ3: 41.75 | AR3: 4.75 | AS3: 10.5 | AT3: 4 | AU3: 1.75 | AY3: 0.75 | BA3: 103.5 | BB3: 1.25 | BC3: 700.75 | BD3: 2.75 | BE3: 27.75 | BF3: 106.5 | BG3: 15.5 | BK3: 49.25 | BL3: 55.25 | BO3: 4.5 | BP3: 10.25 | BQ3: 15.25 | BT3: 14.25 | BX3: 4.5 | BY3: 15.25 | BZ3: 1.25 | CA3: 9 | CB3: 37 | CC3: 59.5 | CD3: 0.75 | CN3: 1.25 | CR3: 8 | CX3: 57.6 | DM3: 0.5 | DN3: 2 | DP3: 32.5 | DQ3: 55.5 | EQ3: 2.75 | ER3: 197.5 | EU3: 3 | EV3: =SUM(B3:EU3) -> 1669.85
A4: Bolay Valérie | B4: 104.5 | C4: 13 | D4: 49 | E4: 10.5 | F4: 121.75 | H4: 311.25 | O4: 1.75 | P4: 1 | Q4: 4 | V4: 5.5 | Y4: 5 | AA4: 9.5 | BK4: 0.25 | BP4: 19 | BT4: 6.25 | BY4: 2.25 | CB4: 28.5 | CC4: 31.5 | CE4: 122 | CJ4: 18.25 | CK4: 6.25 | CM4: 3.5 | CQ4: 7.75 | CR4: 4 | CS4: 0.75 | CX4: 49.6 | DI4: 4.75 | DP4: 29 | DQ4: 36 | DR4: 2.5 | DS4: 111.25 | DT4: 104 | DU4: 30.75 | DV4: 4 | ER4: 142.5 | ES4: 8.75 | EV4: =SUM(B4:EU4) -> 1410.1
A5: Castello Donja | F5: 31.5 | H5: 119.25 | BP5: 2.25 | CB5: 1 | CC5: 16 | CX5: 4 | DP5: 32 | DQ5: 7 | ER5: 36 | EU5: 4 | EV5: =SUM(B5:EU5) -> 253
A6: Chatelain Antonin | AD6: 21.25 | AE6: 234.5 | AF6: 442 | AH6: 23.5 | AI6: 0.5 | AJ6: 3 | AO6: 0.25 | BP6: 0.5 | BQ6: 7.13 | BY6: 24 | CA6: 1.5 | CB6: 38.25 | CC6: 29.75 | CR6: 37 | CX6: 41.6 | DQ6: 42.5 | ER6: 90.5 | EU6: 30 | EV6: =SUM(B6:EU6) -> 1067.73
A7: Chatenoux Didier | AD7: 27 | AE7: 387.75 | AF7: 353.5 | AG7: 268 | AI7: 3 | AJ7: 2 | AL7: 7.5 | AM7: 2.75 | AN7: 2 | AO7: 50.5 | BP7: 45 | BX7: 5.63 | CB7: 43.75 | CC7: 0.25 | CR7: 12 | CX7: 50.4 | DP7: 16 | DQ7: 53 | ER7: 131.5 | EV7: =SUM(B7:EU7) -> 1461.53
A8: Dos Santos Martins Carlos | AP8: 19 | AQ8: 414 | AR8: 155 | AS8: 53.75 | AT8: 50.5 | AU8: 138.5 | AX8: 12.25 | AY8: 8.25 | BQ8: 3 | BT8: 4.5 | BU8: 15.5 | CB8: 23.5 | CC8: 1.5 | CR8: 19.5 | CX8: 36 | DM8: 3 | DQ8: 14.25 | ER8: 70 | EU8: 7 | EV8: =SUM(B8:EU8) -> 1049
A9: Favre Corinne | B9: 294.25 | G9: 1.25 | H9: 171 | I9: 2 | J9: 0.25 | M9: 37.75 | N9: 0.5 | O9: 1.5 | P9: 19.75 | R9: 2.5 | S9: 2 | T9: 0.5 | U9: 2.5 | V9: 100.5 | X9: 16.25 | Y9: 11 | AA9: 0.75 | BP9: 18.5 | BT9: 3.75 | BW9: 0.5 | BX9: 11.51 | CA9: 32.5 | CB9: 80.25 | CC9: 73 | CF9: 1.25 | CJ9: 13 | CK9: 10.75 | CO9: 2.5 | CQ9: 2.75 | CR9: 49.75 | CS9: 5.75 | CU9: 0.5 | CW9: 5.75 | CX9: 43.2 | DK9: 1.75 | DL9: 1 | DN9: 1.75 | DP9: 15.5 | DQ9: 43.75 | DR9: 1 | DS9: 8.75 | DT9: 10.25 | DU9: 12 | EQ9: 0.5 | ER9: 128.5 | EV9: =SUM(B9:EU9) -> 1244.21
A10: Fleuret Thi Hanh | B10: 37.5 | I10: 12 | J10: 11 | L10: 0.25 | AC10: 1.25 | AD10: 0.25 | AO10: 4.75 | AS10: 1.5 | AT10: 1 | AU10: 0.5 | BA10: 1 | BC10: 183.5 | BE10: 0.25 | BF10: 305.75 | BH10: 278 | BK10: 80.5 | BL10: 47.5 | BM10: 15.5 | BO10: 5.75 | BQ10: 21.5 | BT10: 52.63 | BX10: 1.75 | BY10: 2.5 | BZ10: 0.25 | CB10: 14.5 | CC10: 67.25 | CH10: 4 | CR10: 8 | CX10: 50.4 | CY10: 1.5 | CZ10: 2.25 | DA10: 2.75 | DJ10: 1 | DN10: 5.25 | DO10: 10.75 | DP10: 12 | DQ10: 52.25 | DV10: 1 | DZ10: 0.5 | EA10: 2.25 | EG10: 10.75 | EQ10: 8 | ER10: 144 | EV10: =SUM(B10:EU10) -> 1464.78
A11: Galley Laurent | AI11: 0.75 | AO11: 3.75 | AP11: 33.5 | AQ11: 393.75 | AR11: 84.5 | AS11: 107 | AT11: 50.5 | AU11: 27.5 | AV11: 0.75 | AX11: 3.5 | AY11: 28.5 | AZ11: 1.25 | BE11: 0.5 | BQ11: 3.5 | BT11: 2.25 | BV11: 0.75 | BX11: 2 | BY11: 1.75 | CB11: 22 | CC11: 29 | CX11: 36 | DM11: 0.75 | DP11: 121 | DQ11: 8.25 | ER11: 80 | EV11: =SUM(B11:EU11) -> 1043
A12: Geuggis Gilles | AD12: 16.5 | AE12: 52.75 | AF12: 218.75 | AH12: 35.25 | AI12: 4 | AM12: 2 | AO12: 6.75 | BP12: 12 | BX12: 5.63 | CA12: 8.25 | CB12: 7.5 | CC12: 12.5 | CR12: 12.5 | CV12: 3.5 | CX12: 14.4 | DQ12: 1 | ER12: 10 | EV12: =SUM(B12:EU12) -> 423.28
A13: Harth Eric | AD13: 152.5 | AJ13: 3.75 | AM13: 8 | AO13: 0.25 | BP13: 2 | CA13: 56.75 | CB13: 47.5 | CC13: 2 | CE13: 64 | CX13: 20 | DP13: 16 | DQ13: 17.25 | DT13: 3 | DW13: 1.25 | DX13: 26.75 | DY13: 0.5 | EB13: 2.75 | EE13: 190.25 | ER13: 76 | EV13: =SUM(B13:EU13) -> 690.5
A14: Holenweg Pascale | B14: 10.5 | D14: 28 | F14: 251.25 | H14: 304 | P14: 33 | R14: 57 | V14: 38.5 | BP14: 9.5 | BW14: 29.25 | CB14: 9.25 | CC14: 47.25 | CQ14: 14.5 | CR14: 12 | CX14: 39.6 | DI14: 1 | DP14: 20 | DQ14: 23.75 | DS14: 5.25 | DT14: 15.75 | DV14: 50 | ER14: 144 | EV14: =SUM(B14:EU14) -> 1143.35
A15: Kuhn Christian | AD15: 51.5 | AE15: 79.5 | AF15: 154 | AH15: 29.75 | AI15: 3 | AJ15: 1.75 | AL15: 2.5 | AO15: 48.63 | BP15: 2 | BY15: 27.5 | CA15: 0.75 | CB15: 16 | CC15: 15.25 | CX15: 39.2 | DP15: 279.75 | DQ15: 7.75 | DW15: 0.75 | ER15: 114 | EU15: 228.75 | EV15: =SUM(B15:EU15) -> 1102.33
A16: Merzouk Séverine | B16: 28.5 | C16: 13.25 | D16: 79 | E16: 9.25 | F16: 99 | G16: 7.75 | H16: 284 | P16: 88.75 | Q16: 6 | R16: 9 | S16: 13.25 | V16: 15.75 | BP16: 10.5 | BT16: 40 | CB16: 12.5 | CC16: 35 | CF16: 0.25 | CR16: 12 | CS16: 0.75 | CX16: 36 | CY16: 2.75 | DI16: 8.75 | DP16: 43.75 | DQ16: 41.5 | DR16: 9.75 | DT16: 18.25 | DV16: 15 | ER16: 104.5 | EU16: 4 | EV16: =SUM(B16:EU16) -> 1048.75
A17: Meyrat Jean-Marc | B17: 3.75 | X17: 117.5 | Y17: 108.25 | Z17: 125 | AA17: 14.25 | AB17: 4.75 | AE17: 16.25 | AP17: 486 | AX17: 5 | AZ17: 5.5 | BE17: 2.5 | BG17: 80 | BM17: 7.75 | BQ17: 4.75 | BT17: 94.38 | BU17: 43.75 | BV17: 15.25 | BW17: 11.25 | CA17: 20 | CB17: 137 | CC17: 13.5 | CR17: 29.5 | CX17: 57.6 | DP17: 46.5 | DQ17: 4.5 | EA17: 1.5 | EG17: 15 | EL17: 9.5 | EN17: 28 | ER17: 167 | EV17: =SUM(B17:EU17) -> 1675.48
A18: Othenin Roberto | AD18: 3.5 | AE18: 22.75 | AF18: 176 | AM18: 0.25 | AO18: 10 | BP18: 4 | BY18: 1.25 | CB18: 1 | CX18: 5.6 | DQ18: 4.75 | EV18: =SUM(B18:EU18) -> 229.1
A19: Paul Bertram | B19: 7.5 | G19: 0.75 | I19: 20 | J19: 70 | K19: 14.75 | L19: 3.25 | O19: 10 | AB19: 26.25 | AD19: 0.75 | AO19: 1.5 | AQ19: 6.5 | AR19: 0.5 | BA19: 7 | BC19: 17.75 | BE19: 14.25 | BF19: 0.25 | BG19: 74 | BH19: 2.75 | BI19: 49.75 | BK19: 58 | BL19: 182.25 | BM19: 15 | BO19: 23.5 | BQ19: 7.5 | BR19: 0.25 | BS19: 8.25 | BX19: 3 | BY19: 3.5 | BZ19: 0.25 | CB19: 11.5 | CC19: 60.75 | CG19: 2.75 | CL19: 2.25 | CR19: 8 | CT19: 3.5 | CX19: 36 | DC19: 28.5 | DD19: 2 | DG19: 15 | DH19: 1.5 | DM19: 1 | DN19: 0.75 | DQ19: 45.5 | DS19: 1 | EA19: 7 | EB19: 2 | EC19: 8.75 | EE19: 9.75 | EH19: 1.5 | EI19: 0.75 | EJ19: 7.25 | EM19: 1.25 | EQ19: 2.5 | ER19: 140 | ET19: 0.75 | EU19: 20 | EV19: =SUM(B19:EU19) -> 1050.5
A20: Pillet Anne | B20: 23.5 | I20: 1 | O20: 3.5 | P20: 1 | Y20: 2 | AD20: 20.5 | AO20: 17 | AP20: 32 | AQ20: 2.25 | AS20: 0.5 | AU20: 5.25 | AW20: 2.75 | AX20: 10 | BA20: 11.25 | BD20: 1.5 | BE20: 2 | BK20: 0.5 | BP20: 6.75 | BQ20: 41.75 | BR20: 6.25 | BS20: 1 | BT20: 1.75 | BV20: 27 | BX20: 7.25 | BY20: 2.75 | CA20: 169.75 | CB20: 426.5 | CC20: 55.25 | CE20: 219.5 | CP20: 0.5 | CR20: 8 | CX20: 57.6 | DG20: 0.5 | DL20: 1.5 | DM20: 0.25 | DP20: 226.5 | DQ20: 46.5 | DS20: 1 | DU20: 1.75 | ED20: 6.5 | EE20: 36.75 | EF20: 39 | EJ20: 48 | EO20: 35.5 | EP20: 1 | ER20: 252 | EU20: 4 | EV20: =SUM(B20:EU20) -> 1868.85
A21: Rérat Cédric | I21: 12.75 | V21: 0.5 | AO21: 33.25 | AQ21: 0.5 | AT21: 1 | AU21: 2.25 | AX21: 0.5 | BA21: 69.25 | BB21: 39 | BC21: 396.75 | BD21: 33.75 | BE21: 70.75 | BF21: 191 | BG21: 99.5 | BJ21: 0.75 | BK21: 14.75 | BL21: 38.5 | BM21: 0.75 | BN21: 0.5 | BO21: 1 | BP21: 4.75 | BQ21: 7.75 | BT21: 13.25 | BX21: 9.51 | BY21: 3.5 | CA21: 74.75 | CB21: 293.25 | CC21: 238.5 | CN21: 1 | CR21: 46 | CX21: 72 | DK21: 1.75 | DM21: 3.75 | DN21: 5 | DP21: 8 | DQ21: 0.75 | EF21: 109.75 | EJ21: 1.25 | EK21: 4.25 | EQ21: 4.25 | ER21: 176 | ES21: 1 | EV21: =SUM(B21:EU21) -> 2087.01
A22: Rossier Christophe | AD22: 54.75 | AE22: 261 | AF22: 411.5 | AH22: 64 | AI22: 13.5 | AJ22: 9.5 | AK22: 3 | AL22: 7.25 | AM22: 28.5 | AO22: 30.75 | BP22: 63.5 | BX22: 7.13 | BY22: 17 | CA22: 9 | CB22: 78.25 | CC22: 21.25 | CR22: 12 | CV22: 1.5 | CX22: 48 | DI22: 6.5 | DJ22: 7.5 | DP22: 24 | DQ22: 56.25 | DV22: 11 | DW22: 27.75 | DZ22: 18.5 | ER22: 128 | EV22: =SUM(B22:EU22) -> 1420.88
A23: Boulsa Bénévolat | DB23: 0.75 | DF23: 3.75 | EV23: =SUM(B23:EU23) -> 4.5
A24: Klappenbach Sacsahuaman | M24: 125.5 | N24: 8.5 | AY24: 88 | CI24: 2.5 | DE24: 2.5 | EV24: =SUM(B24:EU24) -> 227
A25: reliure bénévoles | BE25: 28.5 | DM25: 14.25 | EV25: =SUM(B25:EU25) -> 42.75
A26: Total | B26: =SUM(B2:B25) -> 510 | C26: =SUM(C2:C25) -> 26.25 | D26: =SUM(D2:D25) -> 156 | E26: =SUM(E2:E25) -> 19.75 | F26: =SUM(F2:F25) -> 503.5 | G26: =SUM(G2:G25) -> 9.75 | H26: =SUM(H2:H25) -> 1189.5 | I26: =SUM(I2:I25) -> 49.5 | ... EU26: =SUM(EU2:EU25) -> 300.75 | EV26: =SUM(B26:EU26) -> 23965.69

Sheet Heures brutes
A1: Collaborateur | B1: 1 | C1: 11C | D1: 11N | E1: 11NC | F1: 11S | G1: 12C | H1: 12S | I1: 13 | J1: 13B | K1: 13C | L1: 13D | M1: 14B | N1: 14D | O1: 16 | P1: 16A | Q1: 16N | R1: 17 | S1: 17E | T1: 18E | U1: 18I | V1: 19 | W1: 1BBR-B | X1: 2 | Y1: 21 | Z1: 24 | AA1: 27 | AB1: 29 | AC1: 2BBR | AD1: 4 | AE1: 41N | AF1: 42N | AG1: 43N | AH1: 44 | AI1: 45 | AJ1: 46C | AK1: 46F | AL1: 46N | AM1: 47 | AN1: 47E | AO1: 49 | AP1: 5 | AQ1: 51 | AR1: 52 | AS1: 53 | AT1: 54 | AU1: 55 | AV1: 55A | AW1: 55E | AX1: 55F | AY1: 56 | AZ1: 5I | BA1: 6 | BB1: 60 | BC1: 61 | BD1: 62 | BE1: 63 | BF1: 64 | BG1: 64A | BH1: 65A | BI1: 65B | BJ1: 67 | BK1: 68 | BL1: 69 | BM1: 69P | BN1: 6DI | BO1: 6I | BP1: 71 | BQ1: 72 | BR1: 72CH | BS1: 72I | BT1: 73 | BU1: 73F | BV1: 74 | BW1: 75 | BX1: 76 | BY1: 76A | BZ1: 76B | CA1: 77 | CB1: 78 | CC1: 79 | CD1: 7I | CE1: A | CF1: A1 | CG1: A13CAL | CH1: A13RA | CI1: A14 | CJ1: A16A | CK1: A16ARA | CL1: A1CAL | CM1: A1RA | CN1: A7CAL | CO1: A7RA | CP1: A7S | CQ1: B1 | CR1: C | CS1: C1 | CT1: C13 | CU1: C7 | CV1: C73 | CW1: CCA24 | CX1: F | CY1: F1 | CZ1: F13 | DA1: F13A | DB1: F13B | DC1: F13CO | DD1: F13FSA | DE1: F14A | DF1: F1B | DG1: F1CO | DH1: F1FSA | DI1: F1VG | DJ1: F4VG | DK1: F7 | DL1: F7A | DM1: F7CO | DN1: F7VG | DO1: I | DP1: M | DQ1: P | DR1: P1 | DS1: P1A | DT1: P1EP | DU1: P1R | DV1: P1VF | DW1: P4 | DX1: P4EP | DY1: P4SD | DZ1: P4VF | EA1: P51 | EB1: P5BV | EC1: P5EP | ED1: P5P | EE1: P5T | EF1: P6A | EG1: P6BT | EH1: P6BV | EI1: P6P | EJ1: P6T | EK1: P6Z | EL1: P72A | EM1: P7C | EN1: P7COM | EO1: P7P | EP1: P7R | EQ1: P7VF | ER1: V | ES1: V1 | ET1: V4G | EU1: Z | EV1: Total
A2: Anderfuhren Sandrine | B2: 3.75 | AM2: 1.25 | AQ2: 50 | AR2: 20.5 | AS2: 1.75 | BC2: 16.25 | BE2: 1.5 | BF2: 9.75 | BG2: 1.5 | BL2: 5.75 | BM2: 10.5 | BQ2: 1.25 | BT2: 10.51 | BU2: 139 | CB2: 1.5 | CC2: 4.25 | CX2: 7.2 | DM2: 2 | EV2: =SUM(B2:EU2) -> 288.21 | EW2: 288.21
A3: Baratti Graziano | I3: 1.75 | M3: 0.25 | N3: 0.5 | O3: 0.25 | AO3: 9 | AQ3: 41.75 | AR3: 4.75 | AS3: 10.5 | AT3: 4 | AU3: 1.75 | AY3: 0.75 | BA3: 103.5 | BB3: 1.25 | BC3: 700.75 | BD3: 2.75 | BE3: 27.75 | BF3: 106.5 | BG3: 15.5 | BK3: 49.25 | BL3: 55.25 | BO3: 4.5 | BP3: 10.25 | BQ3: 15.25 | BT3: 14.25 | BX3: 4.5 | BY3: 15.25 | BZ3: 1.25 | CA3: 9 | CB3: 37 | CC3: 59.5 | CD3: 0.75 | CN3: 1.25 | CR3: 8 | CX3: 57.6 | DM3: 0.5 | DN3: 2 | DP3: 32.5 | DQ3: 55.5 | EQ3: 2.75 | ER3: 197.5 | EU3: 3 | EV3: =SUM(B3:EU3) -> 1669.85 | EW3: 1669.85
A4: Bolay Valérie | B4: 104.5 | C4: 13 | D4: 49 | E4: 10.5 | F4: 121.75 | H4: 311.25 | O4: 1.75 | P4: 1 | Q4: 4 | V4: 5.5 | Y4: 5 | AA4: 9.5 | BK4: 0.25 | BP4: 19 | BT4: 6.25 | BY4: 2.25 | CB4: 28.5 | CC4: 31.5 | CE4: 122 | CJ4: 18.25 | CK4: 6.25 | CM4: 3.5 | CQ4: 7.75 | CR4: 4 | CS4: 0.75 | CX4: 49.6 | DI4: 4.75 | DP4: 29 | DQ4: 36 | DR4: 2.5 | DS4: 111.25 | DT4: 104 | DU4: 30.75 | DV4: 4 | ER4: 142.5 | ES4: 8.75 | EV4: =SUM(B4:EU4) -> 1410.1 | EW4: 1410.1 | FC4: Pour les salariés mensualisés : 1 plein temps = | FG4: 2088 | FH4: A évaluer annuellement (cf circulaire | FK4: R:\COLLABORATIONS_(nationales)\Groupe-des-bibliotheques-suisses(ex_Consortium)\Reportint-controling\comment-decompter-Precisions apres visites des bibliotheques 2015.docx
A5: Castello Donja | F5: 31.5 | H5: 119.25 | BP5: 2.25 | CB5: 1 | CC5: 16 | CX5: 4 | DP5: 32 | DQ5: 7 | ER5: 36 | EU5: 4 | EV5: =SUM(B5:EU5) -> 253 | EW5: 253 | EX5: total des heures payées sur salaire mensuel : | FB5: =SUM(EV2:EV22) -> 23691.44 | FC5: postes à plein temps = | FE5: =FB5/$FG$4 -> 11.346475 | FH5: Pour 2015, considérer 2088 (cf heures dues de CR à 100%)
A6: Chatelain Antonin | AD6: 21.25 | AE6: 234.5 | AF6: 442 | AH6: 23.5 | AI6: 0.5 | AJ6: 3 | AO6: 0.25 | BP6: 0.5 | BQ6: 7.13 | BY6: 24 | CA6: 1.5 | CB6: 38.25 | CC6: 29.75 | CR6: 37 | CX6: 41.6 | DQ6: 42.5 | ER6: 90.5 | EU6: 30 | EV6: =SUM(B6:EU6) -> 1067.73 | EW6: 1067.73
A7: Chatenoux Didier | AD7: 27 | AE7: 387.75 | AF7: 353.5 | AG7: 268 | AI7: 3 | AJ7: 2 | AL7: 7.5 | AM7: 2.75 | AN7: 2 | AO7: 50.5 | BP7: 45 | BX7: 5.63 | CB7: 43.75 | CC7: 0.25 | CR7: 12 | CX7: 50.4 | DP7: 16 | DQ7: 53 | ER7: 131.5 | EV7: =SUM(B7:EU7) -> 1461.53 | EW7: 1461.53
A8: Dos Santos Martins Carlos | AP8: 19 | AQ8: 414 | AR8: 155 | AS8: 53.75 | AT8: 50.5 | AU8: 138.5 | AX8: 12.25 | AY8: 8.25 | BQ8: 3 | BT8: 4.5 | BU8: 15.5 | CB8: 23.5 | CC8: 1.5 | CR8: 19.5 | CX8: 36 | DM8: 3 | DQ8: 14.25 | ER8: 70 | EU8: 7 | EV8: =SUM(B8:EU8) -> 1049 | EW8: 1049 | FC8: Pour les salariés payés à l'heure : 1 plein temps = | FG8: 1900 | FH8: Cf doc de fonctionnement | FJ8: ..\Explications données du reporting 2015-2018 V 16.11.2015.docx
A9: Favre Corinne | B9: 294.25 | G9: 1.25 | H9: 171 | I9: 2 | J9: 0.25 | M9: 37.75 | N9: 0.5 | O9: 1.5 | P9: 19.75 | R9: 2.5 | S9: 2 | T9: 0.5 | U9: 2.5 | V9: 100.5 | X9: 16.25 | Y9: 11 | AA9: 0.75 | BP9: 18.5 | BT9: 3.75 | BW9: 0.5 | BX9: 11.51 | CA9: 32.5 | CB9: 80.25 | CC9: 73 | CF9: 1.25 | CJ9: 13 | CK9: 10.75 | CO9: 2.5 | CQ9: 2.75 | CR9: 49.75 | CS9: 5.75 | CU9: 0.5 | CW9: 5.75 | CX9: 43.2 | DK9: 1.75 | DL9: 1 | DN9: 1.75 | DP9: 15.5 | DQ9: 43.75 | DR9: 1 | DS9: 8.75 | DT9: 10.25 | DU9: 12 | EQ9: 0.5 | ER9: 128.5 | EV9: =SUM(B9:EU9) -> 1244.21 | EW9: 1244.21 | EX9: total des heures payées sur salaire horaire : | FB9: =SUM(EV23:EV25) -> 831.45 | FC9: postes à plein temps = | FE9: =FB9/$FG$8 -> 0.43760526
A10: Galley Laurent | AI10: 0.75 | AO10: 3.75 | AP10: 33.5 | AQ10: 393.75 | AR10: 84.5 | AS10: 107 | AT10: 50.5 | AU10: 27.5 | AV10: 0.75 | AX10: 3.5 | AY10: 28.5 | AZ10: 1.25 | BE10: 0.5 | BQ10: 3.5 | BT10: 2.25 | BV10: 0.75 | BX10: 2 | BY10: 1.75 | CB10: 22 | CC10: 29 | CX10: 36 | DM10: 0.75 | DP10: 121 | DQ10: 8.25 | ER10: 80 | EV10: =SUM(B10:EU10) -> 1043 | EW10: 1043
A11: Geuggis Gilles | AD11: 16.5 | AE11: 52.75 | AF11: 218.75 | AH11: 35.25 | AI11: 4 | AM11: 2 | AO11: 6.75 | BP11: 12 | BX11: 5.63 | CA11: 8.25 | CB11: 7.5 | CC11: 12.5 | CR11: 12.5 | CV11: 3.5 | CX11: 14.4 | DQ11: 1 | ER11: 10 | EV11: =SUM(B11:EU11) -> 423.28 | EW11: 423.28 | FE11: =FE9+FE5 -> 11.78408
A12: Harth Eric | AD12: 152.5 | AJ12: 3.75 | AM12: 8 | AO12: 0.25 | BP12: 2 | CA12: 56.75 | CB12: 47.5 | CC12: 2 | CE12: 64 | CX12: 20 | DP12: 16 | DQ12: 17.25 | DT12: 3 | DW12: 1.25 | DX12: 26.75 | DY12: 0.5 | EB12: 2.75 | EE12: 190.25 | ER12: 76 | EV12: =SUM(B12:EU12) -> 690.5 | EW12: 690.5 | EX12: pour vérif | FC12: Total des activités
A13: Holenweg Pascale | B13: 10.5 | D13: 28 | F13: 251.25 | H13: 304 | P13: 33 | R13: 57 | V13: 38.5 | BP13: 9.5 | BW13: 29.25 | CB13: 9.25 | CC13: 47.25 | CQ13: 14.5 | CR13: 12 | CX13: 39.6 | DI13: 1 | DP13: 20 | DQ13: 23.75 | DS13: 5.25 | DT13: 15.75 | DV13: 50 | ER13: 144 | EV13: =SUM(B13:EU13) -> 1143.35 | EW13: 1143.35 | EX13: =SUM(EV2:EV25) -> 24522.89 | EY13: =FB5+FB9 -> 24522.89 | EZ13: Professionnels : | FB13: =EV27 -> 24522.89 | FC13: postes à plein temps = | FE13: =FE5+FE9 -> 11.78408
A14: Kuhn Christian | AD14: 51.5 | AE14: 79.5 | AF14: 154 | AH14: 29.75 | AI14: 3 | AJ14: 1.75 | AL14: 2.5 | AO14: 48.63 | BP14: 2 | BY14: 27.5 | CA14: 0.75 | CB14: 16 | CC14: 15.25 | CX14: 39.2 | DP14: 279.75 | DQ14: 7.75 | DW14: 0.75 | ER14: 114 | EU14: 228.75 | EV14: =SUM(B14:EU14) -> 1102.33 | EW14: 1102.33 | EZ14: Bénévoles (cf RA ABA) : | FB14: =C64 -> 9944.25 | FC14: postes à plein temps = | FE14: =FB14/1900 -> 5.2338158
A15: Merzouk Séverine | B15: 28.5 | C15: 13.25 | D15: 79 | E15: 9.25 | F15: 99 | G15: 7.75 | H15: 284 | P15: 88.75 | Q15: 6 | R15: 9 | S15: 13.25 | V15: 15.75 | BP15: 10.5 | BT15: 40 | CB15: 12.5 | CC15: 35 | CF15: 0.25 | CR15: 12 | CS15: 0.75 | CX15: 36 | CY15: 2.75 | DI15: 8.75 | DP15: 43.75 | DQ15: 41.5 | DR15: 9.75 | DT15: 18.25 | DV15: 15 | ER15: 104.5 | EU15: 4 | EV15: =SUM(B15:EU15) -> 1048.75 | EW15: 1048.75 | EY15: Bénévoles hors honorifiques (OFAS) | FB15: =C65 -> 9779.25 | FC15: postes à plein temps = | FE15: =I65 -> 5.1469737
A16: Othenin Roberto | AD16: 3.5 | AE16: 22.75 | AF16: 176 | AM16: 0.25 | AO16: 10 | BP16: 4 | BY16: 1.25 | CB16: 1 | CX16: 5.6 | DQ16: 4.75 | EV16: =SUM(B16:EU16) -> 229.1 | EW16: 229.1 | EY16: Heures "absences payées" (vacances…) | FB16: =SUM(EU27+ER27+DQ27+DP27+CX27+CR27+CE27) -> 5603 | FC16: 5603 | FD16: pour sauvegarde
A17: Pillet Anne | B17: 23.5 | I17: 1 | O17: 3.5 | P17: 1 | Y17: 2 | AD17: 20.5 | AO17: 17 | AP17: 32 | AQ17: 2.25 | AS17: 0.5 | AU17: 5.25 | AW17: 2.75 | AX17: 10 | BA17: 11.25 | BD17: 1.5 | BE17: 2 | BK17: 0.5 | BP17: 6.75 | BQ17: 41.75 | BR17: 6.25 | BS17: 1 | BT17: 1.75 | BV17: 27 | BX17: 7.25 | BY17: 2.75 | CA17: 169.75 | CB17: 426.5 | CC17: 55.25 | CE17: 219.5 | CP17: 0.5 | CR17: 8 | CX17: 57.6 | DG17: 0.5 | DL17: 1.5 | DM17: 0.25 | DP17: 226.5 | DQ17: 46.5 | DS17: 1 | DU17: 1.75 | ED17: 6.5 | EE17: 36.75 | EF17: 39 | EJ17: 48 | EO17: 35.5 | EP17: 1 | ER17: 252 | EU17: 4 | EV17: =SUM(B17:EU17) -> 1868.85 | EW17: 1868.85 | EY17: soit Z, V, P, M, F, C, A
A18: Rérat Cédric | I18: 12.75 | V18: 0.5 | AO18: 33.25 | AQ18: 0.5 | AT18: 1 | AU18: 2.25 | AX18: 0.5 | BA18: 69.25 | BB18: 39 | BC18: 396.75 | BD18: 33.75 | BE18: 70.75 | BF18: 191 | BG18: 99.5 | BJ18: 0.75 | BK18: 14.75 | BL18: 38.5 | BM18: 0.75 | BN18: 0.5 | BO18: 1 | BP18: 4.75 | BQ18: 7.75 | BT18: 13.25 | BX18: 9.51 | BY18: 3.5 | CA18: 74.75 | CB18: 293.25 | CC18: 238.5 | CN18: 1 | CR18: 46 | CX18: 72 | DK18: 1.75 | DM18: 3.75 | DN18: 5 | DP18: 8 | DQ18: 0.75 | EF18: 109.75 | EJ18: 1.25 | EK18: 4.25 | EQ18: 4.25 | ER18: 176 | ES18: 1 | EV18: =SUM(B18:EU18) -> 2087.01 | EW18: 2087.01 | EY18: Heures pour administration/overhead | FB18: =EV27-FB16-'Heures productives'!EV48-'Heures productives'!EV33-'Heures productives'!EV34-'Heures productives'!EV35-'Heures productives'!EV36-'Heures productives'!EV37-'Heures productives'!EV38-'Heures productives'!EV39-'Heures productives'!EV40 -> 16822.29
A19: Rossier Christophe | AD19: 54.75 | AE19: 261 | AF19: 411.5 | AH19: 64 | AI19: 13.5 | AJ19: 9.5 | AK19: 3 | AL19: 7.25 | AM19: 28.5 | AO19: 30.75 | BP19: 63.5 | BX19: 7.13 | BY19: 17 | CA19: 9 | CB19: 78.25 | CC19: 21.25 | CR19: 12 | CV19: 1.5 | CX19: 48 | DI19: 6.5 | DJ19: 7.5 | DP19: 24 | DQ19: 56.25 | DV19: 11 | DW19: 27.75 | DZ19: 18.5 | ER19: 128 | EV19: =SUM(B19:EU19) -> 1420.88 | EW19: 1420.88
A20: Fleuret Thi Hanh | B20: 37.5 | I20: 12 | J20: 11 | L20: 0.25 | AC20: 1.25 | AD20: 0.25 | AO20: 4.75 | AS20: 1.5 | AT20: 1 | AU20: 0.5 | BA20: 1 | BC20: 183.5 | BE20: 0.25 | BF20: 305.75 | BH20: 278 | BK20: 80.5 | BL20: 47.5 | BM20: 15.5 | BO20: 5.75 | BQ20: 21.5 | BT20: 52.63 | BX20: 1.75 | BY20: 2.5 | BZ20: 0.25 | CB20: 14.5 | CC20: 67.25 | CH20: 4 | CR20: 8 | CX20: 50.4 | CY20: 1.5 | CZ20: 2.25 | DA20: 2.75 | DJ20: 1 | DN20: 5.25 | DO20: 10.75 | DP20: 12 | DQ20: 52.25 | DV20: 1 | DZ20: 0.5 | EA20: 2.25 | EG20: 10.75 | EQ20: 8 | ER20: 144 | EV20: =SUM(B20:EU20) -> 1464.78 | EW20: 1464.78
A21: Meyrat Jean-Marc | B21: 3.75 | X21: 117.5 | Y21: 108.25 | Z21: 125 | AA21: 14.25 | AB21: 4.75 | AE21: 16.25 | AP21: 486 | AX21: 5 | AZ21: 5.5 | BE21: 2.5 | BG21: 80 | BM21: 7.75 | BQ21: 4.75 | BT21: 94.38 | BU21: 43.75 | BV21: 15.25 | BW21: 11.25 | CA21: 20 | CB21: 137 | CC21: 13.5 | CR21: 29.5 | CX21: 57.6 | DP21: 46.5 | DQ21: 4.5 | EA21: 1.5 | EG21: 15 | EL21: 9.5 | EN21: 28 | ER21: 167 | EV21: =SUM(B21:EU21) -> 1675.48 | EW21: 1675.48
A22: Paul Bertram | B22: 7.5 | G22: 0.75 | I22: 20 | J22: 70 | K22: 14.75 | L22: 3.25 | O22: 10 | AB22: 26.25 | AD22: 0.75 | AO22: 1.5 | AQ22: 6.5 | AR22: 0.5 | BA22: 7 | BC22: 17.75 | BE22: 14.25 | BF22: 0.25 | BG22: 74 | BH22: 2.75 | BI22: 49.75 | BK22: 58 | BL22: 182.25 | BM22: 15 | BO22: 23.5 | BQ22: 7.5 | BR22: 0.25 | BS22: 8.25 | BX22: 3 | BY22: 3.5 | BZ22: 0.25 | CB22: 11.5 | CC22: 60.75 | CG22: 2.75 | CL22: 2.25 | CR22: 8 | CT22: 3.5 | CX22: 36 | DC22: 28.5 | DD22: 2 | DG22: 15 | DH22: 1.5 | DM22: 1 | DN22: 0.75 | DQ22: 45.5 | DS22: 1 | EA22: 7 | EB22: 2 | EC22: 8.75 | EE22: 9.75 | EH22: 1.5 | EI22: 0.75 | EJ22: 7.25 | EM22: 1.25 | EQ22: 2.5 | ER22: 140 | ET22: 0.75 | EU22: 20 | EV22: =SUM(B22:EU22) -> 1050.5 | EW22: 1050.5
A23: Mohnhaupt Martin | CD23: 409 | EV23: =SUM(B23:EU23) -> 409 | EW23: 409
A24: Luc Fontoliet | Z24: 195.45 | EV24: =SUM(B24:EU24) -> 195.45 | EW24: 195.45
A25: Klappenbach Sacsahuaman | M25: 125.5 | N25: 8.5 | AY25: 88 | CI25: 2.5 | DE25: 2.5 | EV25: =SUM(B25:EU25) -> 227 | EW25: 227 | EX25: =SUM(EW2:EW25) -> 24522.89
A26: Bénévoles "actifs" | C26: Dès 2016 ajouter ici les heures des bénévoles pouvant être reconnus "actifs" selon les critères de l'OFAS cf. doc : | L26: ..\..\Informations_pour_realisation\BBR-heures-productives.docx | R26: puis soustraire ces heures pour le RA ABA qui les inclut déjà dans son décompte des heures réalisées par les bénévoles
A27: Total | B27: =SUM(B2:B25) -> 513.75 | C27: =SUM(C2:C25) -> 26.25 | D27: =SUM(D2:D25) -> 156 | E27: =SUM(E2:E25) -> 19.75 | F27: =SUM(F2:F25) -> 503.5 | G27: =SUM(G2:G25) -> 9.75 | H27: =SUM(H2:H25) -> 1189.5 | I27: =SUM(I2:I25) -> 49.5 | ... EU27: =SUM(EU2:EU25) -> 300.75 | EV27: =SUM(B27:EU27) -> 24522.89 | EW27: =SUM(EV2:EV25) -> 24522.89
A28: Total | B28: 510 | C28: 26.25 | D28: 156 | E28: 19.75 | F28: 503.5 | G28: 9.75 | H28: 1189.5 | I28: 49.5 | J28: 81.25 | K28: 14.75 | L28: 3.5 | M28: 163.5 | N28: 9.5 | O28: 17 | P28: 143.5 | Q28: 10 | R28: 68.5 | S28: 15.25 | T28: 0.5 | U28: 2.5 | V28: 160.75 | W28: 3.75 | X28: 133.75 | Y28: 126.25 | Z28: 320.45 | AA28: 24.5 | AB28: 31 | AC28: 1.25 | AD28: 348.5 | AE28: 1054.5 | AF28: 1755.75 | AG28: 268 | AH28: 152.5 | AI28: 24.75 | AJ28: 20 | AK28: 3 | AL28: 17.25 | AM28: 42.75 | AN28: 2 | AO28: 216.38 | AP28: 570.5 | AQ28: 908.75 | AR28: 265.25 | AS28: 175 | AT28: 107 | AU28: 175.75 | AV28: 0.75 | AW28: 2.75 | AX28: 31.25 | AY28: 125.5 | AZ28: 6.75 | BA28: 192 | BB28: 40.25 | BC28: 1315 | BD28: 38 | BE28: 119.5 | BF28: 613.25 | BG28: 270.5 | BH28: 280.75 | BI28: 49.75 | BJ28: 0.75 | BK28: 203.25 | BL28: 329.25 | BM28: 49.5 | BN28: 0.5 | BO28: 34.75 | BP28: 210.5 | BQ28: 113.38 | BR28: 6.5 | BS28: 9.25 | BT28: 243.52 | BU28: 198.25 | BV28: 43 | BW28: 41 | BX28: 57.91 | BY28: 101.25 | BZ28: 1.75 | CA28: 382.25 | CB28: 1330.5 | CC28: 813.25 | CD28: 409.75 | CE28: 405.5 | CF28: 1.5 | CG28: 2.75 | CH28: 4 | CI28: 2.5 | CJ28: 31.25 | CK28: 17 | CL28: 2.25 | CM28: 3.5 | CN28: 2.25 | CO28: 2.5 | CP28: 0.5 | CQ28: 25 | CR28: 278.25 | CS28: 7.25 | CT28: 3.5 | CU28: 0.5 | CV28: 5 | CW28: 5.75 | CX28: 802 | CY28: 4.25 | CZ28: 2.25 | DA28: 2.75 | DB28: 0 | DC28: 28.5 | DD28: 2 | DE28: 2.5 | DF28: 0 | DG28: 15.5 | DH28: 1.5 | DI28: 21 | DJ28: 8.5 | DK28: 3.5 | DL28: 2.5 | DM28: 11.25 | DN28: 14.75 | DO28: 10.75 | DP28: 922.5 | DQ28: 562 | DR28: 13.25 | DS28: 127.25 | DT28: 151.25 | DU28: 44.5 | DV28: 81 | DW28: 29.75 | DX28: 26.75 | DY28: 0.5 | DZ28: 19 | EA28: 10.75 | EB28: 4.75 | EC28: 8.75 | ED28: 6.5 | EE28: 236.75 | EF28: 148.75 | EG28: 25.75 | EH28: 1.5 | EI28: 0.75 | EJ28: 56.5 | EK28: 4.25 | EL28: 9.5 | EM28: 1.25 | EN28: 28 | EO28: 35.5 | EP28: 1 | EQ28: 18 | ER28: 2332 | ES28: 9.75 | ET28: 0.75 | EU28: 300.75 | EV28: 24522.89 | EW28: Ligne pour vérification des totaux et calculs divers (copier et collage spécial - valeur, de la ligne précédente)
A31: Hors heures des professionnels de bibliothèque
A32: Boulsa Bénévolat | DB32: 0.75 | DF32: 3.75 | EV32: =SUM(B32:EU32) -> 4.5
A33: reliure bénévoles | BE33: 28.5 | DM33: 14.25 | EV33: =SUM(B33:EU33) -> 42.75
EX36: =EV27-EU27-ER27-DQ27-DP27-CX27-CR27-CE27-CB27 -> 17589.39
A38: Heures pour travail AI | B38: 0 | C38: rien en 2014, se valide en recherchant les codes AI dans la première ligne du tableau
A41: Pour info :
A42: Explication des couleurs : | B42: Totaux
B43: Payés à l'heure
B44: Handicapés de la vue
B45: Travaux bénévoles hors saisie des heures travaillées à la BBR
B46: Heures absences payées
A50: Calcul du travail des bénévoles | C50: Pour les bénévoles : 1 plein temps = | F50: 1900
A52: Reliure + commission BBR :
A53: dames reliure+envoi cat | C53: =EV33 -> 42.75 | I53: =C53/$F$50 -> 0.0225
A54: Boulsa | C54: =EV32 -> 4.5 | I54: =C54/$F$50 -> 0.0023684211
A55: Bénévoles commission BBR | C55: 165 | I55: =C55/$F$50 -> 0.086842105
A56: Total commBBR + reliure | C56: =SUM(C53:C55) -> 212.25 | H56: postes | I56: =SUM(I53:I55) -> 0.11171053 | J56: =C56/F50 -> 0.11171053 | K56: pour validation total I46
A58: Production :
A59: Livre Parlé (numérique) | C59: =G71 -> 5209.5 | D59: soit heures enregistrées x 3.0 | H59: soit : | I59: =C59/$F$50 -> 2.7418421
A60: Braille | C60: =E79 -> 4522.5 | D60: soit pour les bénévoles chaque page braille x 0.09 | I60: =C60/$F$50 -> 2.3802632
A61: Boulsa | C61: 0 | I61: =C61/$F$50 -> 0
A62: Total production | C62: =SUM(C59:C61) -> 9732 | H62: postes | I62: =SUM(I59:I61) -> 5.1221053 | J62: =C62/F50 -> 5.1221053 | K62: pour validation total I52
A64: Total général du bénévolat | C64: =C62+C56 -> 9944.25 | I64: =I62+I56 -> 5.2338158 | J64: =C64/F50 -> 5.2338158 | K64: pour validation total I54
B65: hors honorifiques | C65: =C64-C55 -> 9779.25 | I65: =I64-I55 -> 5.1469737
A67: Détails pour évaluation de la production des Bénévoles :
A69: LP : compter le nombre d'heures produites et le transformer en heures travaillées (CD x 3.0)
F70: en décimal
B71: ='Heures audio produites-recap'!E36 -> 72.357639 | C71: CD- enregistrés BBR + votations... (voir feuille prod audio) | F71: =B71*3 -> 217.07292 | G71: 5209.5 | H71: heures pour enregistrements de CD (=heures x3)
B72: ='Heures audio produites-recap'!E13 -> 68.809722 | C72: CD- BSR + partenaires
B73: ='Heures audio produites-recap'!E11 -> 38.601389 | C73: CD-retraitement anciennes cass BBR+ commerce (=daisyfication)
B74: 0 | C74: Prod synthèse vocale
A77: Braille : compter le nombre de pages braille produites par les bénévoles (xxx-TRIM.xls de la prod) et le transformer en heures travaillées ( 1p. Braille x 0.09)
B79: ='[1]Cumul trimestriels'!$E$105 -> 50250 | C79: 50250 | E79: =B79*0.09 -> 4522.5 | F79: heures de transcription par les bénévoles (en décimal)

Sheet Heures productives
A1: Collaborateur | B1: 1 | C1: 11C | D1: 11N | E1: 11NC | F1: 11S | G1: 12C | H1: 12S | I1: 13 | J1: 13B | K1: 13C | L1: 13D | M1: 14B | N1: 14D | O1: 16 | P1: 16A | Q1: 16N | R1: 17 | S1: 17E | T1: 18E | U1: 18I | V1: 19 | W1: 1BBR-B | X1: 2 | Y1: 21 | Z1: 24 | AA1: 27 | AB1: 29 | AC1: 2BBR | AD1: 4 | AE1: 41N | AF1: 42N | AG1: 43N | AH1: 44 | AI1: 45 | AJ1: 46C | AK1: 46F | AL1: 46N | AM1: 47 | AN1: 47E | AO1: 49 | AP1: 5 | AQ1: 51 | AR1: 52 | AS1: 53 | AT1: 54 | AU1: 55 | AV1: 55A | AW1: 55E | AX1: 55F | AY1: 56 | AZ1: 5I | BA1: 6 | BB1: 60 | BC1: 61 | BD1: 62 | BE1: 63 | BF1: 64 | BG1: 64A | BH1: 65A | BI1: 65B | BJ1: 67 | BK1: 68 | BL1: 69 | BM1: 69P | BN1: 6DI | BO1: 6I | BP1: 71 | BQ1: 72 | BR1: 72CH | BS1: 72I | BT1: 73 | BU1: 73F | BV1: 74 | BW1: 75 | BX1: 76 | BY1: 76A | BZ1: 76B | CA1: 77 | CB1: 78 | CC1: 79 | CD1: 7I | CE1: A | CF1: A1 | CG1: A13CAL | CH1: A13RA | CI1: A14 | CJ1: A16A | CK1: A16ARA | CL1: A1CAL | CM1: A1RA | CN1: A7CAL | CO1: A7RA | CP1: A7S | CQ1: B1 | CR1: C | CS1: C1 | CT1: C13 | CU1: C7 | CV1: C73 | CW1: CCA24 | CX1: F | CY1: F1 | CZ1: F13 | DA1: F13A | DB1: F13B | DC1: F13CO | DD1: F13FSA | DE1: F14A | DF1: F1B | DG1: F1CO | DH1: F1FSA | DI1: F1VG | DJ1: F4VG | DK1: F7 | DL1: F7A | DM1: F7CO | DN1: F7VG | DO1: I | DP1: M | DQ1: P | DR1: P1 | DS1: P1A | DT1: P1EP | DU1: P1R | DV1: P1VF | DW1: P4 | DX1: P4EP | DY1: P4SD | DZ1: P4VF | EA1: P51 | EB1: P5BV | EC1: P5EP | ED1: P5P | EE1: P5T | EF1: P6A | EG1: P6BT | EH1: P6BV | EI1: P6P | EJ1: P6T | EK1: P6Z | EL1: P72A | EM1: P7C | EN1: P7COM | EO1: P7P | EP1: P7R | EQ1: P7VF | ER1: V | ES1: V1 | ET1: V4G | EU1: Z | EV1: Total
A2: Anderfuhren Sandrine | B2: 3.75 | AM2: 1.25 | AP2: 1.5 | AQ2: 50 | AR2: 20.5 | AS2: 1.75 | BC2: 16.25 | BE2: 1.5 | BF2: 9.75 | BG2: 1.5 | BL2: 5.75 | BM2: 10.5 | BQ2: 1.25 | BT2: 10.51 | BU2: 139 | DM2: 2 | EV2: =SUM(B2:EU2) -> 276.76 | EW2: 276.76
A3: Baratti Graziano | I3: 1.75 | M3: 0.25 | N3: 0.5 | O3: 0.25 | AO3: 9 | AQ3: 41.75 | AR3: 4.75 | AS3: 10.5 | AT3: 4 | AU3: 1.75 | AY3: 0.75 | BA3: =103.5+37 -> 140.5 | BB3: 1.25 | BC3: 700.75 | BD3: 2.75 | BE3: 27.75 | BF3: 106.5 | BG3: 15.5 | BK3: 49.25 | BL3: 55.25 | BO3: 4.5 | BP3: 10.25 | BQ3: 15.25 | BT3: 14.25 | BX3: 4.5 | BY3: 15.25 | BZ3: 1.25 | CA3: 9 | CD3: 0.75 | CN3: 1.25 | DM3: 0.5 | DN3: 2 | EQ3: 2.75 | EV3: =SUM(B3:EU3) -> 1256.25 | EW3: 1256.25
A4: Bolay Valérie | B4: =104.5+28.5 -> 133 | C4: 13 | D4: 49 | E4: 10.5 | F4: 121.75 | H4: 311.25 | O4: 1.75 | P4: 1 | Q4: 4 | V4: 5.5 | Y4: 5 | AA4: 9.5 | BK4: 0.25 | BP4: 19 | BT4: 6.25 | BY4: 2.25 | CJ4: 18.25 | CK4: 6.25 | CM4: 3.5 | CQ4: 7.75 | CS4: 0.75 | DI4: 4.75 | DR4: 2.5 | DS4: 111.25 | DT4: 104 | DU4: 30.75 | DV4: 4 | ES4: 8.75 | EV4: =SUM(B4:EU4) -> 995.5 | EW4: 995.5
A5: Castello Donja | B5: 1 | F5: 31.5 | H5: 119.25 | BP5: 2.25 | EV5: =SUM(B5:EU5) -> 154 | EW5: 154
A6: Chatelain Antonin | AD6: =21.25+38.25 -> 59.5 | AE6: 234.5 | AF6: 442 | AH6: 23.5 | AI6: 0.5 | AJ6: 3 | AO6: 0.25 | BP6: 0.5 | BQ6: 7.13 | BY6: 24 | CA6: 1.5 | EV6: =SUM(B6:EU6) -> 796.38 | EW6: 796.38
A7: Chatenoux Didier | AD7: =27+43.75 -> 70.75 | AE7: 387.75 | AF7: 353.5 | AG7: 268 | AI7: 3 | AJ7: 2 | AL7: 7.5 | AM7: 2.75 | AN7: 2 | AO7: 50.5 | BP7: 45 | BX7: 5.63 | EV7: =SUM(B7:EU7) -> 1198.38 | EW7: 1198.38
A8: Dos Santos Martins Carlos | AP8: =19+23.5 -> 42.5 | AQ8: 414 | AR8: 155 | AS8: 53.75 | AT8: 50.5 | AU8: 138.5 | AX8: 12.25 | AY8: 8.25 | BQ8: 3 | BT8: 4.5 | BU8: 15.5 | DM8: 3 | EV8: =SUM(B8:EU8) -> 900.75 | EW8: 900.75
A9: Favre Corinne | B9: =294.25+40.25 -> 334.5 | G9: 1.25 | H9: 171 | I9: 2 | J9: 0.25 | M9: 37.75 | N9: 0.5 | O9: 1.5 | P9: 19.75 | R9: 2.5 | S9: 2 | T9: 0.5 | U9: 2.5 | V9: 100.5 | X9: 16.25 | Y9: 11 | AA9: 0.75 | BP9: 18.5 | BT9: 3.75 | BW9: 0.5 | BX9: 11.51 | CA9: 32.5 | CF9: 1.25 | CJ9: 13 | CK9: 10.75 | CO9: 2.5 | CQ9: 2.75 | CS9: 5.75 | CU9: 0.5 | CW9: 5.75 | DK9: 1.75 | DL9: 1 | DN9: 1.75 | DR9: 1 | DS9: 8.75 | DT9: 10.25 | DU9: 12 | EQ9: 0.5 | EV9: =SUM(B9:EU9) -> 850.51 | EW9: 850.51
A10: Galley Laurent | AI10: 0.75 | AO10: 3.75 | AP10: =33.5+22 -> 55.5 | AQ10: 393.75 | AR10: 84.5 | AS10: 107 | AT10: 50.5 | AU10: 27.5 | AV10: 0.75 | AX10: 3.5 | AY10: 28.5 | AZ10: 1.25 | BE10: 0.5 | BQ10: 3.5 | BT10: 2.25 | BV10: 0.75 | BX10: 2 | BY10: 1.75 | DM10: 0.75 | EV10: =SUM(B10:EU10) -> 768.75 | EW10: 768.75
A11: Geuggis Gilles | AD11: =16.5+7.5 -> 24 | AE11: 52.75 | AF11: 218.75 | AH11: 35.25 | AI11: 4 | AM11: 2 | AO11: 6.75 | BP11: 12 | BX11: 5.63 | CA11: 8.25 | CV11: 3.5 | EV11: =SUM(B11:EU11) -> 372.88 | EW11: 372.88
A12: Harth Eric | AD12: =152.5+24 -> 176.5 | AJ12: 3.75 | AM12: 8 | AO12: 0.25 | BP12: 2 | CA12: 56.75 | DT12: 3 | DW12: 1.25 | DX12: 26.75 | DY12: 0.5 | EB12: 2.75 | EE12: 190.25 | EV12: =SUM(B12:EU12) -> 471.75 | EW12: 471.75
A13: Holenweg Pascale | B13: =10.5+9.25 -> 19.75 | D13: 28 | F13: 251.25 | H13: 304 | P13: 33 | R13: 57 | V13: 38.5 | BP13: 9.5 | BW13: 29.25 | CQ13: 14.5 | DI13: 1 | DS13: 5.25 | DT13: 15.75 | DV13: 50 | EV13: =SUM(B13:EU13) -> 856.75 | EW13: 856.75
A14: Kuhn Christian | AD14: =51.5+16 -> 67.5 | AE14: 79.5 | AF14: 154 | AH14: 29.75 | AI14: 3 | AJ14: 1.75 | AL14: 2.5 | AO14: 48.63 | BP14: 2 | BY14: 27.5 | CA14: 0.75 | DW14: 0.75 | EV14: =SUM(B14:EU14) -> 417.63 | EW14: 417.63
A15: Merzouk Séverine | B15: =28.5+12.5 -> 41 | C15: 13.25 | D15: 79 | E15: 9.25 | F15: 99 | G15: 7.75 | H15: 284 | P15: 88.75 | Q15: 6 | R15: 9 | S15: 13.25 | V15: 15.75 | BP15: 10.5 | BT15: 40 | CF15: 0.25 | CS15: 0.75 | CY15: 2.75 | DI15: 8.75 | DR15: 9.75 | DT15: 18.25 | DV15: 15 | EV15: =SUM(B15:EU15) -> 772 | EW15: 772
A16: Othenin Roberto | AD16: =3.5+1 -> 4.5 | AE16: 22.75 | AF16: 176 | AM16: 0.25 | AO16: 10 | BP16: 4 | BY16: 1.25 | EV16: =SUM(B16:EU16) -> 218.75 | EW16: 218.75
A17: Pillet Anne | B17: 23.5 | I17: 1 | O17: 3.5 | P17: 1 | Y17: 2 | AD17: 20.5 | AO17: 17 | AP17: 32 | AQ17: 2.25 | AS17: 0.5 | AU17: 5.25 | AW17: 2.75 | AX17: 10 | BA17: 11.25 | BD17: 1.5 | BE17: 2 | BK17: 0.5 | BP17: 6.75 | BQ17: 41.75 | BR17: 6.25 | BS17: 1 | BT17: 1.75 | BV17: 27 | BX17: 7.25 | BY17: 2.75 | CA17: 169.75 | CP17: 0.5 | DG17: 0.5 | DL17: 1.5 | DM17: 0.25 | DS17: 1 | DU17: 1.75 | ED17: 6.5 | EE17: 36.75 | EF17: 39 | EJ17: 48 | EO17: 35.5 | EP17: 1 | EV17: =SUM(B17:EU17) -> 573 | EW17: 573
A18: Rérat Cédric | I18: 12.75 | V18: 0.5 | AD18: 40 | AO18: 33.25 | AP18: 70 | AQ18: 0.5 | AT18: 1 | AU18: 2.25 | AX18: 0.5 | BA18: =69.25+40 -> 109.25 | BB18: 39 | BC18: 396.75 | BD18: 33.75 | BE18: 70.75 | BF18: 191 | BG18: 99.5 | BJ18: 0.75 | BK18: 14.75 | BL18: 38.5 | BM18: 0.75 | BN18: 0.5 | BO18: 1 | BP18: 4.75 | BQ18: 7.75 | BT18: 13.25 | BX18: 9.51 | BY18: 3.5 | CA18: 74.75 | CN18: 1 | DK18: 1.75 | DM18: 3.75 | DN18: 5 | EF18: 109.75 | EJ18: 1.25 | EK18: 4.25 | EQ18: 4.25 | ES18: 1 | EV18: =SUM(B18:EU18) -> 1402.51 | EW18: 1402.51
A19: Rossier Christophe | AD19: =54.75+39 -> 93.75 | AE19: 261 | AF19: 411.5 | AH19: 64 | AI19: 13.5 | AJ19: 9.5 | AK19: 3 | AL19: 7.25 | AM19: 28.5 | AO19: 30.75 | BP19: 63.5 | BX19: 7.13 | BY19: 17 | CA19: 9 | CV19: 1.5 | DI19: 6.5 | DJ19: 7.5 | DV19: 11 | DW19: 27.75 | DZ19: 18.5 | EV19: =SUM(B19:EU19) -> 1092.13 | EW19: 1092.13
A20: Fleuret Thi Hanh | B20: 37.5 | I20: 12 | J20: 11 | L20: 0.25 | AC20: 1.25 | AD20: 0.25 | AO20: 4.75 | AS20: 1.5 | AT20: 1 | AU20: 0.5 | BA20: 1 | BC20: 183.5 | BE20: 0.25 | BF20: 305.75 | BH20: 278 | BK20: =80.5+14.5 -> 95 | BL20: 47.5 | BM20: 15.5 | BO20: 5.75 | BQ20: 21.5 | BT20: 52.63 | BX20: 1.75 | BY20: 2.5 | BZ20: 0.25 | CH20: 4 | CY20: 1.5 | CZ20: 2.25 | DA20: 2.75 | DJ20: 1 | DN20: 5.25 | DO20: 10.75 | DV20: 1 | DZ20: 0.5 | EA20: 2.25 | EG20: 10.75 | EQ20: 8 | EV20: =SUM(B20:EU20) -> 1130.88 | EW20: 1130.88
A21: Meyrat Jean-Marc | B21: 3.75 | X21: 117.5 | Y21: 108.25 | Z21: 125 | AA21: 14.25 | AB21: 4.75 | AE21: 16.25 | AP21: =486+69 -> 555 | AX21: 5 | AZ21: 5.5 | BE21: 2.5 | BG21: 80 | BM21: 7.75 | BQ21: 4.75 | BT21: 94.38 | BU21: 43.75 | BV21: 15.25 | BW21: 11.25 | CA21: 20 | EA21: 1.5 | EG21: 15 | EL21: 9.5 | EN21: 28 | EV21: =SUM(B21:EU21) -> 1288.88 | EW21: 1288.88
A22: Paul Bertram | B22: 7.5 | G22: 0.75 | I22: 20 | J22: 70 | K22: 14.75 | L22: 3.25 | O22: 10 | AB22: 26.25 | AD22: 0.75 | AO22: 1.5 | AQ22: 6.5 | AR22: 0.5 | BA22: 7 | BC22: 17.75 | BE22: 14.25 | BF22: 0.25 | BG22: 74 | BH22: 2.75 | BI22: 49.75 | BK22: =58+11.5 -> 69.5 | BL22: 182.25 | BM22: 15 | BO22: 23.5 | BQ22: 7.5 | BR22: 0.25 | BS22: 8.25 | BX22: 3 | BY22: 3.5 | BZ22: 0.25 | CG22: 2.75 | CL22: 2.25 | CT22: 3.5 | DC22: 28.5 | DD22: 2 | DG22: 15 | DH22: 1.5 | DM22: 1 | DN22: 0.75 | DS22: 1 | EA22: 7 | EB22: 2 | EC22: 8.75 | EE22: 9.75 | EH22: 1.5 | EI22: 0.75 | EJ22: 7.25 | EM22: 1.25 | EQ22: 2.5 | ET22: 0.75 | EV22: =SUM(B22:EU22) -> 740.25 | EW22: 740.25
A23: Mohnhaupt Martin | CD23: 409 | EV23: =SUM(B23:EU23) -> 409 | EW23: 409
A24: Luc Fontoliet | Z24: 195.45 | EV24: =SUM(B24:EU24) -> 195.45 | EW24: 195.45
A25: Klappenbach Sacsahuaman | M25: 125.5 | N25: 8.5 | AY25: 88 | CI25: 2.5 | DE25: 2.5 | EV25: =SUM(B25:EU25) -> 227 | EW25: 227 | EX25: =SUM(EW2:EW25) -> 17366.14
A26: Total | B26: =SUM(B2:B25) -> 605.25 | C26: =SUM(C2:C25) -> 26.25 | D26: =SUM(D2:D25) -> 156 | E26: =SUM(E2:E25) -> 19.75 | F26: =SUM(F2:F25) -> 503.5 | G26: =SUM(G2:G25) -> 9.75 | H26: =SUM(H2:H25) -> 1189.5 | I26: =SUM(I2:I25) -> 49.5 | ... S26: =SUM(S2:S25) -> 15.25 | V26: =SUM(V2:V25) -> 160.75 | W26: =SUM(W2:W25) -> 0 | AB26: =SUM(AB2:AB25) -> 31 | AC26: =SUM(AC2:AC25) -> 1.25 | AD26: =SUM(AD2:AD25) -> 558 | AE26: =SUM(AE2:AE25) -> 1054.5 | AF26: =SUM(AF2:AF25) -> 1755.75 | AG26: =SUM(AG2:AG25) -> 268 | AH26: =SUM(AH2:AH25) -> 152.5 | AI26: =SUM(AI2:AI25) -> 24.75 | ... BJ26: =SUM(BJ2:BJ25) -> 0.75 | BL26: =SUM(BL2:BL25) -> 329.25 | BM26: =SUM(BM2:BM25) -> 49.5 | BN26: =SUM(BN2:BN25) -> 0.5 | BO26: =SUM(BO2:BO25) -> 34.75 | BU26: =SUM(BU2:BU25) -> 198.25 | BX26: =SUM(BX2:BX25) -> 57.91 | BY26: =SUM(BY2:BY25) -> 101.25 | BZ26: =SUM(BZ2:BZ25) -> 1.75 | CD26: =SUM(CD2:CD25) -> 409.75 | CF26: =SUM(CF2:CF25) -> 1.5 | CG26: =SUM(CG2:CG25) -> 2.75 | CH26: =SUM(CH2:CH25) -> 4 | CK26: =SUM(CK2:CK25) -> 17 | CL26: =SUM(CL2:CL25) -> 2.25 | CM26: =SUM(CM2:CM25) -> 3.5 | CN26: =SUM(CN2:CN25) -> 2.25 | CO26: =SUM(CO2:CO25) -> 2.5 | CS26: =SUM(CS2:CS25) -> 7.25 | CT26: =SUM(CT2:CT25) -> 3.5 | CU26: =SUM(CU2:CU25) -> 0.5 | DO26: =SUM(DO2:DO25) -> 10.75 | DR26: =SUM(DR2:DR25) -> 13.25 | DS26: =SUM(DS2:DS25) -> 127.25 | DT26: =SUM(DT2:DT25) -> 151.25 | DU26: =SUM(DU2:DU25) -> 44.5 | DV26: =SUM(DV2:DV25) -> 81 | DW26: =SUM(DW2:DW25) -> 29.75 | DX26: =SUM(DX2:DX25) -> 26.75 | DY26: =SUM(DY2:DY25) -> 0.5 | DZ26: =SUM(DZ2:DZ25) -> 19 | EB26: =SUM(EB2:EB25) -> 4.75 | EC26: =SUM(EC2:EC25) -> 8.75 | ED26: =SUM(ED2:ED25) -> 6.5 | EE26: =SUM(EE2:EE25) -> 236.75 | EF26: =SUM(EF2:EF25) -> 148.75 | EG26: =SUM(EG2:EG25) -> 25.75 | EH26: =SUM(EH2:EH25) -> 1.5 | EI26: =SUM(EI2:EI25) -> 0.75 | ... EK26: =SUM(EK2:EK25) -> 4.25 | EM26: =SUM(EM2:EM25) -> 1.25 | EN26: =SUM(EN2:EN25) -> 28 | EO26: =SUM(EO2:EO25) -> 35.5 | EP26: =SUM(EP2:EP25) -> 1 | EQ26: =SUM(EQ2:EQ25) -> 18 | ES26: =SUM(ES2:ES25) -> 9.75 | ET26: =SUM(ET2:ET25) -> 0.75 | EV26: =SUM(B26:EU26) -> 15268.54 | EW26: =SUM(EV2:EV25) -> 17366.14
A27: Total | B27: 605.25 | C27: 26.25 | D27: 156 | E27: 19.75 | F27: 503.5 | G27: 9.75 | H27: 1189.5 | I27: 49.5 | J27: 81.25 | K27: 14.75 | L27: 3.5 | M27: 163.5 | N27: 9.5 | O27: 17 | P27: 143.5 | Q27: 10 | R27: 68.5 | S27: 15.25 | V27: 160.75 | W27: 0 | AB27: 31 | AC27: 1.25 | AD27: 558 | AE27: 1054.5 | AF27: 1755.75 | AG27: 268 | AH27: 152.5 | AI27: 24.75 | AJ27: 20 | AK27: 3 | AL27: 17.25 | AM27: 42.75 | AN27: 2 | AO27: 216.38 | AP27: 756.5 | AQ27: 908.75 | AR27: 265.25 | AS27: 175 | AT27: 107 | AU27: 175.75 | AV27: 0.75 | AW27: 2.75 | AX27: 31.25 | AY27: 125.5 | AZ27: 6.75 | BA27: 269 | BB27: 40.25 | BC27: 1315 | BD27: 38 | BE27: 119.5 | BF27: 613.25 | BG27: 270.5 | BH27: 280.75 | BI27: 49.75 | BJ27: 0.75 | BL27: 329.25 | BM27: 49.5 | BN27: 0.5 | BO27: 34.75 | BU27: 198.25 | BX27: 57.91 | BY27: 101.25 | BZ27: 1.75 | CD27: 409.75 | CF27: 1.5 | CG27: 2.75 | CH27: 4 | CK27: 17 | CL27: 2.25 | CM27: 3.5 | CN27: 2.25 | CO27: 2.5 | CS27: 7.25 | CT27: 3.5 | CU27: 0.5 | DO27: 10.75 | DR27: 13.25 | DS27: 127.25 | DT27: 151.25 | DU27: 44.5 | DV27: 81 | DW27: 29.75 | DX27: 26.75 | DY27: 0.5 | DZ27: 19 | EB27: 4.75 | EC27: 8.75 | ED27: 6.5 | EE27: 236.75 | EF27: 148.75 | EG27: 25.75 | EH27: 1.5 | EI27: 0.75 | EJ27: 56.5 | EK27: 4.25 | EM27: 1.25 | EN27: 28 | EO27: 35.5 | EP27: 1 | EQ27: 18 | ES27: 9.75 | ET27: 0.75 | EV27: 15268.54 | EW27: 17366.14 | EX27: Ligne pour vérification des totaux et calculs divers (copier et collage spécial - valeur, de la ligne précédente)
A30: Heures improductives overhead
A31: Heures pour absences payées (service civile, militaire, maladies…) | CE31: ='Heures brutes'!CE28 -> 405.5 | CR31: ='Heures brutes'!CR28 -> 278.25 | CX31: ='Heures brutes'!CX28 -> 802 | DP31: ='Heures brutes'!DP28 -> 922.5 | DQ31: ='Heures brutes'!DQ28 -> 562 | ER31: ='Heures brutes'!ER28 -> 2332 | EU31: ='Heures brutes'!EU28 -> 300.75 | EV31: =SUM(B31:EU31) -> 5603 | EW31: heures non productives
A32: Heures improductives pour overhead… | CB32: 740.5 | CC32: ='Heures brutes'!CC28 -> 813.25 | EV32: =SUM(B32:EU32) -> 1553.75 | EW32: heures non productives
A33: Relecture de documents internes (orghographe…) | CP33: =SUM(CP2:CP25) -> 0.5 | CQ33: =SUM(CQ2:CQ25) -> 25 | EV33: =SUM(B33:EU33) -> 25.5 | EW33: heures non productives
A34: Conseils orientation en réception | BK34: =SUM(BK2:BK25) -> 229.25 | EV34: =SUM(B34:EU34) -> 229.25 | EW34: heures non productives
A35: Relations publiques ( bibliothèques publiques, consortium, bibliothèques étrangères, CIR) | BQ35: =SUM(BQ2:BQ25) -> 113.38 | BR35: =SUM(BR2:BR25) -> 6.5 | BS35: =SUM(BS2:BS25) -> 9.25 | CV35: =SUM(CV2:CV25) -> 5 | EV35: =SUM(B35:EU35) -> 134.13 | EW35: heures non productives
A36: Représentations externes | BV36: =SUM(BV2:BV25) -> 43 | BW36: =SUM(BW2:BW25) -> 41 | EV36: =SUM(B36:EU36) -> 84 | EW36: heures non productives
A37: Gestion du personnel | CA37: =SUM(CA2:CA25) -> 382.25 | EV37: =SUM(B37:EU37) -> 382.25 | EW37: heures non productives
A38: Manutentions/relectures pour l'ABA | CI38: =SUM(CI2:CI25) -> 2.5 | CJ38: =SUM(CJ2:CJ25) -> 31.25 | EV38: =SUM(B38:EU38) -> 33.75 | EW38: heures non productives
A39: Animation braille | BT39: =SUM(BT2:BT25) -> 243.52 | EV39: =SUM(B39:EU39) -> 243.52 | EW39: heures non productives
A40: Entretien des locaux | BP40: =SUM(BP2:BP25) -> 210.5 | EV40: =SUM(B40:EU40) -> 210.5 | EW40: heures non productives
EV41: =SUM(EV31:EV40) -> 8499.65
A43: Heures improductives à signaler à LM pour transmission ou non au CCA ou CIR | FB43: Prestations facturées totales | FF43: =EV44 -> 120.75
A44: Prestations facturées | CY44: =SUM(CY2:CY25) -> 4.25 | CZ44: =SUM(CZ2:CZ25) -> 2.25 | DA44: =SUM(DA2:DA25) -> 2.75 | DB44: =SUM(DB2:DB25) -> 0 | DC44: =SUM(DC2:DC25) -> 28.5 | DD44: =SUM(DD2:DD25) -> 2 | DE44: =SUM(DE2:DE25) -> 2.5 | DF44: =SUM(DF2:DF25) -> 0 | ... DN44: =SUM(DN2:DN25) -> 14.75 | EV44: =SUM(B44:EU44) -> 120.75 | EW44: non productives BBR, facturées
A45: CCA (+ interventions BBR) | X45: =SUM(X2:X25) -> 133.75 | Y45: =SUM(Y2:Y25) -> 126.25 | Z45: =SUM(Z2:Z25) -> 320.45 | AA45: =SUM(AA2:AA25) -> 24.5 | CW45: =SUM(CW2:CW25) -> 5.75 | EL45: =SUM(EL2:EL25) -> 9.5 | EV45: =SUM(B45:EU45) -> 620.2 | EW45: non productives BBR, annoncées CCA | FB45: Prestations factuées réalisées par des collègues HdV | FF45: =SUM(CY20:DN22) -> 61.5
A46: Conseils en accessibilité (BBR) | T46: =SUM(T2:T22) -> 0.5 | U46: =SUM(U2:U22) -> 2.5 | EV46: =SUM(B46:EU46) -> 3 | EW46: non productives BBR, annoncées CCA | FB46: Prestations facturées réalisés par collègues voyants | FF46: =FF43-FF45 -> 59.25
A47: Projet "remise à niveau connaissances braille" | EA47: =SUM(EA2:EA25) -> 10.75 | EV47: =SUM(B47:EU47) -> 10.75 | EW47: non productives BBR, annoncées CCA | FF47: =SUM(FF45:FF46) -> 120.75
EV48: =SUM(EV44:EV47) -> 754.7
EW49: total général | EX49: §
EW50: Heures pour produit (y compris CCA et facturées) | FA50: =SUM(EV26,EV44,EV45,EV46,EV47) -> 16023.24
EW51: Heures non productives hors CCA | FA51: =SUM(EV33:EV40) -> 1342.9
FA52: =SUM(FA50:FA51) -> 17366.14
A54: Hors heures des professionnels de bibliothèque | EZ54: Pour décompte SBS / OFAS
A55: Boulsa Bénévolat | DB55: 0.75 | DF55: 3.75 | EV55: =SUM(B55:EU55) -> 4.5
A56: reliure bénévoles | BE56: 28.5 | DM56: 14.25 | EV56: =SUM(B56:EU56) -> 42.75
EV57: =SUM(EV55:EV56) -> 47.25 | EZ57: heures non productives
FB61: =SUM(FA62:FA63) -> 21626.24
EW62: Heures absences payées | FA62: ='Heures brutes'!FB16 -> 5603
ES63: Pour le doc ofas / SBS | EV63: en heures | EW63: Heures pour produit totales (BBR + CCA + facturées) | FA63: =FA50 -> 16023.24
ES64: heures productives | EU64: =FA64 -> 15268.54 | EV64: 15268:32 | EW64: Heures pour produit réelles (sans les prestations vendues-SANS CCA) | FA64: =EV26 -> 15268.54
A65: Heures pour travail AI | B65: 0 | C65: rien en 2014, se valide en recherchant les codes AI dans la première ligne du tableau | EW65: Heures brutes prof. BBR y compris heures vendues | FA65: ='Heures brutes'!EV27 -> 24522.89 | FB65: poste à plein temps (total) | FD65: ='Heures brutes'!FE13 -> 11.78408
ES66: heures brutes professionnels | EU66: =FA66 -> 24402.14 | EV66: 24402:08 | EW66: Heures brutes prof. BBR (sans prestations vendues AVEC CCA) | FA66: =FA65-EV44 -> 24402.14 | FB66: poste à plein temps (hors prest.v) | FD66: =FD65-FA80 -> 11.72625
ES67: heures absences payées | EU67: =FA67 -> 5603 | EV67: 233.45833 | EW67: Heures manquantes (vac, f, cours…) | FA67: =EV31 -> 5603
A68: Pour info : | ES68: Heures non productives | EU68: =FA68+FA69+FA70 -> 3530.6 | EV68: 147.08611 | EW68: Heures travaillées non productives BBR | FA68: =SUM(EV33:EV40) -> 1342.9
A69: Explication des couleurs : | B69: Totaux | EW69: Heures travaillées portées au CCA | FA69: =SUM(EV45:EV47) -> 633.95
B70: Payés à l'heure | ES70: total improductif | EU70: =EU68+EU67 -> 9133.6 | EW70: Heures overhead non prod gestion (partie des 78 + 79) | FA70: =EV32 -> 1553.75
B71: Handicapés de la vue | EW71: Heures pour prestations payées
B72: Travaux bénévoles hors saisie des heures travaillées à la BBR | EW72: Votations genevoises | FA72: =SUM(DI44:DJ44,DN44) -> 44.25
B73: Heures absences payées | EW73: Transcription documents FSA | FA73: =DH44+DG44 -> 17 | FB73: réalisées par collègue HdV
EW74: Gestion des prod FSA | FA74: =DM44 -> 11.25
EW75: Impression FSA | FA75: =DD44+DC44 -> 30.5 | FB75: réalisées par collègue HdV
EW76: Petites prod diverses payées | FA76: =CY44+CZ44+DL44 -> 9
EW77: Animations payées | FA77: 0
EW78: Impression Algerie | FA78: =DA44+DE44+DK44 -> 8.75 | FB78: réalisées par collègue HdV
EX79: Total heures payées | FA79: =SUM(FA72:FA78) -> 120.75
FA80: =FA79/2088 -> 0.05783046 | FB80: Poste à plein temps pour prestations vendues

Sheet Heures audio produites-recap
A1: Récapitulatif général : | C1: Chiffres de digibook | D1: NetBib | H1: MOT de pass pour modif des cellules protégées = OFAS
D2: titres | E2: heures | F2: minutes | H2: remarques et usage dans la stat ofas
A3: Adjonction totale au catalogue | D3: =D6+D8+D11+D13+D17 -> 537 | E3: =E17+E8+E11+E13-E17+E6 -> 178.71597 | H3: pour validation avec les extractions NetBiblio
D4: soit | E4: XX | H4: !!! En cas de légère différence entre l'info Digibook et NetBiblio, les infos retenues sont celles de NetBiblio. Si la différence est importante, en trouver la source
A6: repiquage anciens enregistrements conservés nouvellement ajoutés à la collection | C6: 0 | D6: 0 | E6: 0 | F6: 0
A8: Total prod BBR (stu+domicile) : | C8: 246 | D8: ='Heures audio prod-extrNetBiblio'!B263 -> 246 | E8: ='Heures audio prod-extrNetBiblio'!M263 -> 71.304861 | H8: à compter dans les heures produites par la BBR et utiliser pour évaluer le temps de travail des bénévoles dans le fichier excel extrait de la saisie des heures (heures produites x 3)
H9: studio | I9: 206 titres, 1439 h. 46 min (NetBib)
H10: domicile | I10: 40 titres, 271 h 33 min (NetBib)
A11: Total copies commerce daisyfiées (=commerce seul) | C11: 119 | D11: ='Heures audio prod-extrNetBiblio'!B388 -> 119 | E11: ='Heures audio prod-extrNetBiblio'!M388 -> 38.601389 | H11: à ajouter aux heures produites par la BBR, idem gros travaux de daisyfication, si très petit, les intégrer simplement dans le total de la prod BBR tel que provenant de Digibook
A13: Total copies hors prod BBR (BSR-LBB…-hors commerce) | C13: 172 | D13: ='Heures audio prod-extrNetBiblio'!B604 -> 172 | E13: ='Heures audio prod-extrNetBiblio'!M604 -> 68.809722 | H13: ne comptabiliser que comme des heure de copies dans entretien ancienne collection
D14: soit | E14: =SUM(E6:E13) -> 178.71597
A16: Productions diverses
A17: Total daisyfication et redaisyfication (de Digibook) qui ne sont pas annoncés dans le catalogue car déjà signalés sous forme de cassette | D17: 0 | E17: 0 | F17: 0 | H17: DANS LA STAT OFAS : à ajouter aux heures produites par la BBR, dans Digibook "dossiers-DAISIFICATIONS…", n'inclut pas les les copies du commerce qui sont comptabilisées dans "commerce"
E18: =E17+(ROUNDDOWN(F17/60,0)) -> 0 | F18: =F17-(ROUNDDOWN(F17/60,0)*60) -> 0
A20: Cas particuliers (Digibook) - à évaluer | D20: 0 | E20: 0 | H20: !!! Synthèse vocale à compter séparément : au cas par cas : 2012
A21: Votations | C21: 5 votations en X exempalires) | D21: 5 | E21: 0.30208333 | H21: à compter dans les heures produites par la BBR et utiliser pour évaluer le temps de travail des bénévoles dans le fichier excel extrait de la saisie des heures (heures XXXX)
A22: autre | B22: 1x Gazette vallon | D22: 1 | E22: 0.020138889
A23: Rapport annuel ABA | D23: 0 | E23: 0 | H23: à compter dans les heures produites par la BBR et utiliser pour évaluer le temps de travail des bénévoles dans le fichier excel extrait de la saisie des heures (heures XXXX)
A24: Calp + catalo thématiques | D24: 4 | E24: 0.73055556 | H24: à compter dans les heures produites par la BBR et utiliser pour évaluer le temps de travail des bénévoles dans le fichier excel extrait de la saisie des heures (heures XXXX)
C25: TOTAL prod div | D25: =SUM(D20:D24) -> 10 | E25: =SUM(E20:E24) -> 1.0527778
A26: Nbr de documents traités par les studios durant l'année | D26: =D24+D23+D22+D21+D20+D17+D13+D11+D8+D6 -> 547
A27: Totaux Divers | F27: comptabiliser toutes les copies qui se font sur les graveurs et les répartir sur les grilles Ofas en fonction de leurs particularités
A28: Productions des bénévoles
A29: Prod par BBR (stu+dom+votations+calp)
A30: Stud + domicile | D30: =D8 -> 246 | E30: =E8 -> 71.304861 | I30: Pour décompte heures prod bénévoles
A31: votations | D31: =D21 -> 5 | E31: =E21 -> 0.30208333 | I31: Pour décompte heures prod bénévoles
A32: autres | D32: =D22 -> 1 | E32: =E22 -> 0.020138889 | I32: Pour décompte heures prod bénévoles
A33: RA ABA | D33: =D23 -> 0 | E33: =E23 -> 0 | I33: Pour décompte heures prod bénévoles
A34: Calp + catalo thématiques | D34: =D24 -> 4 | E34: =E24 -> 0.73055556 | I34: Pour décompte heures prod bénévoles en fonction du réalisateur des documents de l'année
A35: cas particuliers | D35: =D20 -> 0 | E35: =E20 -> 0
D36: =SUM(D30:D35) -> 256 | E36: =SUM(E30:E35) -> 72.357639 | F36: 72.357639
A38: Daisyfications et redaisyf. de livres non annoncés comme nouveautés | D38: =D17+D6 -> 0 | E38: =E17+E6 -> 0 | G38: à utiliser pour remplir la stat prod OFAS et compter comme heure produite par la BBR
A39: commerce | D39: =D11 -> 119 | E39: =E11 -> 38.601389
D40: =SUM(D38:D39) -> 119 | E40: =SUM(E38:E39) -> 38.601389
A42: Prod synthèse vocale | D42: 0 | E42: 0
A44: Echanges
A45: Copies de l'extérieur sans retouches(LBB…) | D45: =D13 -> 172 | E45: =E13 -> 68.809722 | F45: =F14 -> 0 | G45: ne comptabiliser que comme des heure de copies dans entretien ancienne collection
E47: =E42+E40+E36+E25+E14 -> 290.72778 | G47: Total prod audio
A628: Donc :
A629: stats ofas, total heures numérisées = | D629: =E17+#REF!+#REF! -> #REF!
A630: dont heures numérisées seulement = | D630: =E17+#REF! -> #REF!
A631: stats heures bénévoles = | D631: =#REF!*3 -> #REF!
A633: stat ofas, titres produits = | D633: =D17+#REF!+#REF! -> #REF!
A634: dont tites numérisés seulement = | D634: =D17+#REF! -> #REF!

Sheet Heures audio prod-extrNetBiblio
A1: 1 | B1: No de notice | C1: Auteur | D1: Titre | E1: Nombre de vol./durée | F1: compter le nbr de caractères pour créer la fonction si | G1: extraire les heures | H1: convertir le texte en heures | I1: extraire les minutes | J1: Eliminer le texte min. | K1: convertir en numérique | L1: concaténer les h et min | M1: convertir en nbr et lui donner le fomat numérique [hh]:mm | N1: Note générale | O1: Cote | P1: Fournisseur | Q1: Appartenance
A2: 2 | B2: 7513A100 | C2: Eriksen, Endre Lund | D2: Super | E2: 5 h. 45 min. | F2: =LEN(E2) -> 12 | G2: =IF(F2=12,LEFT(E2,1),LEFT(E2,2)) -> 5 | H2: =VALUE(G2) -> 5 | I2: =RIGHT(E2,7) -> 45 min. | J2: =LEFT(I2,2) -> 45 | K2: =VALUE(J2) -> 45 | L2: =H2&":"&K2 -> 5:45 | M2: =VALUE(L2) -> 0.23958333 | N2: Mme Aline Sauter Caillet, 2015 | O2: 1.99 | P2: BBR-enregistrement à domicile | Q2: BBR
A3: 3 | B3: 7515A100 | C3: Lugon-Moulin, Roland | D3: Double schuss | E3: 8 h. 43 min. | F3: =LEN(E3) -> 12 | G3: =IF(F3=12,LEFT(E3,1),LEFT(E3,2)) -> 8 | H3: =VALUE(G3) -> 8 | I3: =RIGHT(E3,7) -> 43 min. | J3: =LEFT(I3,2) -> 43 | K3: =VALUE(J3) -> 43 | L3: =H3&":"&K3 -> 8:43 | M3: =VALUE(L3) -> 0.36319444 | N3: M. Serge Kneuss, 2014 | O3: 1.1 | P3: BBR-enregistrement à domicile | Q3: BBR
A4: 4 | B4: 7522A100 | C4: Pigani, Paola | D4: N'entre pas dans mon âme avec tes chaussures | E4: 6 h. 08 min. | F4: =LEN(E4) -> 12 | G4: =IF(F4=12,LEFT(E4,1),LEFT(E4,2)) -> 6 | H4: =VALUE(G4) -> 6 | I4: =RIGHT(E4,7) -> 08 min. | J4: =LEFT(I4,2) -> 08 | K4: =VALUE(J4) -> 8 | L4: =H4&":"&K4 -> 6:8 | M4: =VALUE(L4) -> 0.25555556 | N4: Mme Lorenza Eder, 2015 | O4: 1.1 | P4: BBR-enregistrement à domicile | Q4: BBR
A5: 5 | B5: 7524A100 | C5: Arnaud, Claude | D5: Proust contre Cocteau | E5: 5 h. 19 min. | F5: =LEN(E5) -> 12 | G5: =IF(F5=12,LEFT(E5,1),LEFT(E5,2)) -> 5 | H5: =VALUE(G5) -> 5 | I5: =RIGHT(E5,7) -> 19 min. | J5: =LEFT(I5,2) -> 19 | K5: =VALUE(J5) -> 19 | L5: =H5&":"&K5 -> 5:19 | M5: =VALUE(L5) -> 0.22152778 | N5: M. Willy Bulliard, 2015 | O5: 9.82 | P5: BBR-enregistrement à domicile | Q5: BBR
A6: 6 | B6: 7535A100 | C6: Cuneo, Anne | D6: Gatti's variétés : roman | E6: 9 h. 02 min. | F6: =LEN(E6) -> 12 | G6: =IF(F6=12,LEFT(E6,1),LEFT(E6,2)) -> 9 | H6: =VALUE(G6) -> 9 | I6: =RIGHT(E6,7) -> 02 min. | J6: =LEFT(I6,2) -> 02 | K6: =VALUE(J6) -> 2 | L6: =H6&":"&K6 -> 9:2 | M6: =VALUE(L6) -> 0.37638889 | N6: M. Serge Kneuss, 2015 | O6: 1.12 | P6: BBR-enregistrement à domicile | Q6: BBR
A7: 7 | B7: 7543A100 | C7: Sternhell, Zeev | D7: Ni droite ni gauche : l'idéologie fasciste en France | E7: 27 h. 16 min. | F7: =LEN(E7) -> 13 | G7: =IF(F7=12,LEFT(E7,1),LEFT(E7,2)) -> 27 | H7: =VALUE(G7) -> 27 | I7: =RIGHT(E7,7) -> 16 min. | J7: =LEFT(I7,2) -> 16 | K7: =VALUE(J7) -> 16 | L7: =H7&":"&K7 -> 27:16 | M7: =VALUE(L7) -> 1.1361111 | N7: Mme Marielle Gracieux, 2015 | O7: 9.32 | P7: BBR-enregistrement à domicile | Q7: BBR
A8: 8 | B8: 7628A100 | C8: Orban, Jean-Pierre | D8: Vera : roman | E8: 6 h. 46 min. | F8: =LEN(E8) -> 12 | G8: =IF(F8=12,LEFT(E8,1),LEFT(E8,2)) -> 6 | H8: =VALUE(G8) -> 6 | I8: =RIGHT(E8,7) -> 46 min. | J8: =LEFT(I8,2) -> 46 | K8: =VALUE(J8) -> 46 | L8: =H8&":"&K8 -> 6:46 | M8: =VALUE(L8) -> 0.28194444 | N8: Mme Françoise Assimacopoulos, 2015 | O8: 1.1 | P8: BBR-enregistrement à domicile | Q8: BBR
A9: 9 | B9: 7637A100 | C9: Grisham, John | D9: Calico Joe : roman | E9: 5 h. 20 min. | F9: =LEN(E9) -> 12 | G9: =IF(F9=12,LEFT(E9,1),LEFT(E9,2)) -> 5 | H9: =VALUE(G9) -> 5 | I9: =RIGHT(E9,7) -> 20 min. | J9: =LEFT(I9,2) -> 20 | K9: =VALUE(J9) -> 20 | L9: =H9&":"&K9 -> 5:20 | M9: =VALUE(L9) -> 0.22222222 | N9: M. Jacques Deschenaux, 2015 | O9: 1.1 | P9: BBR-enregistrement à domicile | Q9: BBR
A10: 10 | B10: 7645A100 | D10: Philippe Favre : pressé de vivre : ses amis témoignent | E10: 3 h. 25 min. | F10: =LEN(E10) -> 12 | G10: =IF(F10=12,LEFT(E10,1),LEFT(E10,2)) -> 3 | H10: =VALUE(G10) -> 3 | I10: =RIGHT(E10,7) -> 25 min. | J10: =LEFT(I10,2) -> 25 | K10: =VALUE(J10) -> 25 | L10: =H10&":"&K10 -> 3:25 | M10: =VALUE(L10) -> 0.14236111 | N10: M. Jacques Deschenaux, 2015 | O10: 7.5 | P10: BBR-enregistrement à domicile | Q10: BBR
A11: 11 | B11: 7648A100 | C11: Cosnay, Marie | D11: Le fils de Judith | E11: 1 h. 57 min. | F11: =LEN(E11) -> 12 | G11: =IF(F11=12,LEFT(E11,1),LEFT(E11,2)) -> 1 | H11: =VALUE(G11) -> 1 | I11: =RIGHT(E11,7) -> 57 min. | J11: =LEFT(I11,2) -> 57 | K11: =VALUE(J11) -> 57 | L11: =H11&":"&K11 -> 1:57 | M11: =VALUE(L11) -> 0.08125 | N11: Mme Manuela Bezzi, 2015 | O11: 1.1 | P11: BBR-enregistrement à domicile | Q11: BBR
A12: 12 | B12: 7656A100 | C12: Frisco, Sonia | D12: Le portail de l'ange : roman | E12: 8 h. 13 min. | F12: =LEN(E12) -> 12 | G12: =IF(F12=12,LEFT(E12,1),LEFT(E12,2)) -> 8 | H12: =VALUE(G12) -> 8 | I12: =RIGHT(E12,7) -> 13 min. | J12: =LEFT(I12,2) -> 13 | K12: =VALUE(J12) -> 13 | L12: =H12&":"&K12 -> 8:13 | M12: =VALUE(L12) -> 0.34236111 | N12: Mme Françoise Assimacopoulos, 2015 | O12: 1.1 | P12: BBR-enregistrement à domicile | Q12: BBR
A13: 13 | B13: 7663A100 | C13: Hug, Nathalie | D13: 1, rue des petits pas : roman | E13: 9 h. 01 min. | F13: =LEN(E13) -> 12 | G13: =IF(F13=12,LEFT(E13,1),LEFT(E13,2)) -> 9 | H13: =VALUE(G13) -> 9 | I13: =RIGHT(E13,7) -> 01 min. | J13: =LEFT(I13,2) -> 01 | K13: =VALUE(J13) -> 1 | L13: =H13&":"&K13 -> 9:1 | M13: =VALUE(L13) -> 0.37569444 | N13: Mme Françoise Assimacopoulos, 2015 | O13: 1.1 | P13: BBR-enregistrement à domicile | Q13: BBR
A14: 14 | B14: 7666A100 | C14: Hosseini, Khaled | D14: Ainsi résonne l'écho infini des montagnes | E14: 13 h. 12 min. | F14: =LEN(E14) -> 13 | G14: =IF(F14=12,LEFT(E14,1),LEFT(E14,2)) -> 13 | H14: =VALUE(G14) -> 13 | I14: =RIGHT(E14,7) -> 12 min. | J14: =LEFT(I14,2) -> 12 | K14: =VALUE(J14) -> 12 | L14: =H14&":"&K14 -> 13:12 | M14: =VALUE(L14) -> 0.55 | N14: M. Bernard Wurstemberger, 2015 | O14: 1.1 | P14: BBR-enregistrement à domicile | Q14: BBR
A15: 15 | B15: 7667A100 | C15: Brett, Lily | D15: Lola Bensky | E15: 9 h. 27 min. | F15: =LEN(E15) -> 12 | G15: =IF(F15=12,LEFT(E15,1),LEFT(E15,2)) -> 9 | H15: =VALUE(G15) -> 9 | I15: =RIGHT(E15,7) -> 27 min. | J15: =LEFT(I15,2) -> 27 | K15: =VALUE(J15) -> 27 | L15: =H15&":"&K15 -> 9:27 | M15: =VALUE(L15) -> 0.39375 | N15: Mme Lorenza Eder, 2015 | O15: 1.1 | P15: BBR-enregistrement à domicile | Q15: BBR
A16: 16 | B16: 7669A100 | C16: Salbert, Marc | D16: De l'influence du lancer de minibar sur l'engagement humanitaire | E16: 5 h. 10 min. | F16: =LEN(E16) -> 12 | G16: =IF(F16=12,LEFT(E16,1),LEFT(E16,2)) -> 5 | H16: =VALUE(G16) -> 5 | I16: =RIGHT(E16,7) -> 10 min. | J16: =LEFT(I16,2) -> 10 | K16: =VALUE(J16) -> 10 | L16: =H16&":"&K16 -> 5:10 | M16: =VALUE(L16) -> 0.21527778 | N16: Mme Françoise Assimacopoulos, 2015 | O16: 1.1 | P16: BBR-enregistrement à domicile | Q16: BBR
A17: 17 | B17: 7730A100 | C17: Markaris, Petros | D17: [Une enquête de Kostas Charitos] : [1] : Liquidation à la grecque | E17: 7 h. 59 min. | F17: =LEN(E17) -> 12 | G17: =IF(F17=12,LEFT(E17,1),LEFT(E17,2)) -> 7 | H17: =VALUE(G17) -> 7 | I17: =RIGHT(E17,7) -> 59 min. | J17: =LEFT(I17,2) -> 59 | K17: =VALUE(J17) -> 59 | L17: =H17&":"&K17 -> 7:59 | M17: =VALUE(L17) -> 0.33263889 | N17: M. Willy Bulliard, 2015 | O17: 1.2 | P17: BBR-enregistrement à domicile | Q17: BBR
A18: 18 | B18: 7762A100 | C18: Bauwen, Patrick | D18: Seul à savoir : roman | E18: 10 h. 56 min. | F18: =LEN(E18) -> 13 | G18: =IF(F18=12,LEFT(E18,1),LEFT(E18,2)) -> 10 | H18: =VALUE(G18) -> 10 | I18: =RIGHT(E18,7) -> 56 min. | J18: =LEFT(I18,2) -> 56 | K18: =VALUE(J18) -> 56 | L18: =H18&":"&K18 -> 10:56 | M18: =VALUE(L18) -> 0.45555556 | N18: Mme Aline Sauter Caillet, 2015 | O18: 1.2 | P18: BBR-enregistrement à domicile | Q18: BBR
A19: 19 | B19: 7767A100 | C19: Grosmaire, Jean-Louis | D19: Tu n'aurais pas dû partir | E19: 9 h. 27 min. | F19: =LEN(E19) -> 12 | G19: =IF(F19=12,LEFT(E19,1),LEFT(E19,2)) -> 9 | H19: =VALUE(G19) -> 9 | I19: =RIGHT(E19,7) -> 27 min. | J19: =LEFT(I19,2) -> 27 | K19: =VALUE(J19) -> 27 | L19: =H19&":"&K19 -> 9:27 | M19: =VALUE(L19) -> 0.39375 | N19: M. Jean-Pierre Abel, 2015 | O19: 1.1 | P19: BBR-enregistrement à domicile | Q19: BBR
A20: 20 | B20: 7779A100 | C20: Giraldi, William | D20: Aucun homme ni dieu : roman | E20: 7 h. 00 min. | F20: =LEN(E20) -> 12 | G20: =IF(F20=12,LEFT(E20,1),LEFT(E20,2)) -> 7 | H20: =VALUE(G20) -> 7 | I20: =RIGHT(E20,7) -> 00 min. | J20: =LEFT(I20,2) -> 00 | K20: =VALUE(J20) -> 0 | L20: =H20&":"&K20 -> 7:0 | M20: =VALUE(L20) -> 0.29166667 | N20: Mme Annick Perruchoud, 2015 | O20: 1.1 | P20: BBR-enregistrement à domicile | Q20: BBR
A21: 21 | B21: 7780A100 | C21: Giannoni, Chantal | D21: Encorselée : récit | E21: 2 h. 08 min. | F21: =LEN(E21) -> 12 | G21: =IF(F21=12,LEFT(E21,1),LEFT(E21,2)) -> 2 | H21: =VALUE(G21) -> 2 | I21: =RIGHT(E21,7) -> 08 min. | J21: =LEFT(I21,2) -> 08 | K21: =VALUE(J21) -> 8 | L21: =H21&":"&K21 -> 2:8 | M21: =VALUE(L21) -> 0.088888889 | N21: Mme Françoise Grousson, 2015 | O21: 2 | P21: BBR-enregistrement à domicile | Q21: BBR
A22: 22 | B22: 7787A100 | C22: Rumiz, Paolo | D22: Le phare, voyage immobile | E22: 3 h. 53 min. | F22: =LEN(E22) -> 12 | G22: =IF(F22=12,LEFT(E22,1),LEFT(E22,2)) -> 3 | H22: =VALUE(G22) -> 3 | I22: =RIGHT(E22,7) -> 53 min. | J22: =LEFT(I22,2) -> 53 | K22: =VALUE(J22) -> 53 | L22: =H22&":"&K22 -> 3:53 | M22: =VALUE(L22) -> 0.16180556 | N22: M. Willy Bulliard, 2015 | O22: 5 | P22: BBR-enregistrement à domicile | Q22: BBR
... A30: 30 | B30: 7890A100 | C30: Matzneff, Gabriel | D30: La lettre au capitaine Brunner : roman | E30: 6 h. 16 min. | F30: =LEN(E30) -> 12 | G30: =IF(F30=12,LEFT(E30,1),LEFT(E30,2)) -> 6 | H30: =VALUE(G30) -> 6 | I30: =RIGHT(E30,7) -> 16 min. | J30: =LEFT(I30,2) -> 16 | K30: =VALUE(J30) -> 16 | L30: =H30&":"&K30 -> 6:16 | M30: =VALUE(L30) -> 0.26111111 | N30: M. Willy Bulliard, 2015 | O30: 1.1 | P30: BBR-enregistrement à domicile | Q30: BBR
A31: 31 | B31: 7892A100 | D31: Genève sang dessus dessous : 5 fictions policières | E31: 6 h. 09 min. | F31: =LEN(E31) -> 12 | G31: =IF(F31=12,LEFT(E31,1),LEFT(E31,2)) -> 6 | H31: =VALUE(G31) -> 6 | I31: =RIGHT(E31,7) -> 09 min. | J31: =LEFT(I31,2) -> 09 | K31: =VALUE(J31) -> 9 | L31: =H31&":"&K31 -> 6:9 | M31: =VALUE(L31) -> 0.25625 | N31: M. Jacques Deschenaux, 2015 | O31: 1.8 | P31: BBR-enregistrement à domicile | Q31: BBR
A32: 32 | B32: 7896A100 | C32: Izner, Claude | D32: Le dragon du Trocadéro : inédit | E32: 10 h. 49 min. | F32: =LEN(E32) -> 13 | G32: =IF(F32=12,LEFT(E32,1),LEFT(E32,2)) -> 10 | H32: =VALUE(G32) -> 10 | I32: =RIGHT(E32,7) -> 49 min. | J32: =LEFT(I32,2) -> 49 | K32: =VALUE(J32) -> 49 | L32: =H32&":"&K32 -> 10:49 | M32: =VALUE(L32) -> 0.45069444 | N32: Mme Marie-Clély Ladini, 2015 | O32: 1.2 | P32: BBR-enregistrement à domicile | Q32: BBR
A33: 33 | B33: 7898A100 | C33: Juhel, Fabienne | D33: La chaise numéro 14 | E33: 7 h. 56 min. | F33: =LEN(E33) -> 12 | G33: =IF(F33=12,LEFT(E33,1),LEFT(E33,2)) -> 7 | H33: =VALUE(G33) -> 7 | I33: =RIGHT(E33,7) -> 56 min. | J33: =LEFT(I33,2) -> 56 | K33: =VALUE(J33) -> 56 | L33: =H33&":"&K33 -> 7:56 | M33: =VALUE(L33) -> 0.33055556 | N33: Mme Aline Sauter Caillet, 2015 | O33: 1.1 | P33: BBR-enregistrement à domicile | Q33: BBR
A34: 34 | B34: 7906A100 | C34: Buti, Roland | D34: Luce & Célie | E34: 4 h. 33 min. | F34: =LEN(E34) -> 12 | G34: =IF(F34=12,LEFT(E34,1),LEFT(E34,2)) -> 4 | H34: =VALUE(G34) -> 4 | I34: =RIGHT(E34,7) -> 33 min. | J34: =LEFT(I34,2) -> 33 | K34: =VALUE(J34) -> 33 | L34: =H34&":"&K34 -> 4:33 | M34: =VALUE(L34) -> 0.18958333 | N34: Mme Françoise Assimacopoulos, 2015 | O34: 1.1 | P34: BBR-enregistrement à domicile | Q34: BBR
A35: 35 | B35: 7909A100 | C35: Cochard, Zara | D35: Choisir la vie | E35: 3 h. 40 min. | F35: =LEN(E35) -> 12 | G35: =IF(F35=12,LEFT(E35,1),LEFT(E35,2)) -> 3 | H35: =VALUE(G35) -> 3 | I35: =RIGHT(E35,7) -> 40 min. | J35: =LEFT(I35,2) -> 40 | K35: =VALUE(J35) -> 40 | L35: =H35&":"&K35 -> 3:40 | M35: =VALUE(L35) -> 0.15277778 | N35: Mme Françoise Assimacopoulos, 2015 | O35: 7.5 | P35: BBR-enregistrement à domicile | Q35: BBR
A36: 36 | B36: 7911A100 | C36: Duluc, Vincent | D36: Le cinquième Beatles : roman | E36: 4 h. 55 min. | F36: =LEN(E36) -> 12 | G36: =IF(F36=12,LEFT(E36,1),LEFT(E36,2)) -> 4 | H36: =VALUE(G36) -> 4 | I36: =RIGHT(E36,7) -> 55 min. | J36: =LEFT(I36,2) -> 55 | K36: =VALUE(J36) -> 55 | L36: =H36&":"&K36 -> 4:55 | M36: =VALUE(L36) -> 0.20486111 | N36: M. Jacques Deschenaux, 2015 | O36: 1.1 | P36: BBR-enregistrement à domicile | Q36: BBR
A37: 37 | B37: 7937A100 | C37: Ragougneau, Alexis | D37: La madone de Notre-Dame | E37: 5 h. 55 min. | F37: =LEN(E37) -> 12 | G37: =IF(F37=12,LEFT(E37,1),LEFT(E37,2)) -> 5 | H37: =VALUE(G37) -> 5 | I37: =RIGHT(E37,7) -> 55 min. | J37: =LEFT(I37,2) -> 55 | K37: =VALUE(J37) -> 55 | L37: =H37&":"&K37 -> 5:55 | M37: =VALUE(L37) -> 0.24652778 | N37: Mme Marielle Gracieux, 2015 | O37: 1.2 | P37: BBR-enregistrement à domicile | Q37: BBR
A38: 38 | B38: 7945A100 | C38: Brécart, Anne | D38: La femme provisoire | E38: 4 h. 20 min. | F38: =LEN(E38) -> 12 | G38: =IF(F38=12,LEFT(E38,1),LEFT(E38,2)) -> 4 | H38: =VALUE(G38) -> 4 | I38: =RIGHT(E38,7) -> 20 min. | J38: =LEFT(I38,2) -> 20 | K38: =VALUE(J38) -> 20 | L38: =H38&":"&K38 -> 4:20 | M38: =VALUE(L38) -> 0.18055556 | N38: Mme Françoise Grousson, 2015 | O38: 1.1 | P38: BBR-enregistrement à domicile | Q38: BBR
A39: 39 | B39: 7972A100 | C39: Charnay, Désiré | D39: Madagascar : carnet de voyage en 1862 | E39: 2 h. 10 min. | F39: =LEN(E39) -> 12 | G39: =IF(F39=12,LEFT(E39,1),LEFT(E39,2)) -> 2 | H39: =VALUE(G39) -> 2 | I39: =RIGHT(E39,7) -> 10 min. | J39: =LEFT(I39,2) -> 10 | K39: =VALUE(J39) -> 10 | L39: =H39&":"&K39 -> 2:10 | M39: =VALUE(L39) -> 0.090277778 | N39: M. Marc-Aurèle Dubois-Pelerin, 2015 | O39: 5 | P39: BBR-enregistrement à domicile | Q39: BBR
A40: 40 | B40: 8050A100 | C40: Lapaque, Sébastien | D40: La théorie de Rio de Janeiro | E40: 2 h. 45 min. | F40: =LEN(E40) -> 12 | G40: =IF(F40=12,LEFT(E40,1),LEFT(E40,2)) -> 2 | H40: =VALUE(G40) -> 2 | I40: =RIGHT(E40,7) -> 45 min. | J40: =LEFT(I40,2) -> 45 | K40: =VALUE(J40) -> 45 | L40: =H40&":"&K40 -> 2:45 | M40: =VALUE(L40) -> 0.11458333 | N40: Mme Marielle Gracieux, 2015 | O40: 7.1 | P40: BBR-enregistrement à domicile | Q40: BBR
A41: 41 | B41: 8052A100 | C41: Weber, Anne | D41: Vaterland : récit | E41: 7 h. 11 min. | F41: =LEN(E41) -> 12 | G41: =IF(F41=12,LEFT(E41,1),LEFT(E41,2)) -> 7 | H41: =VALUE(G41) -> 7 | I41: =RIGHT(E41,7) -> 11 min. | J41: =LEFT(I41,2) -> 11 | K41: =VALUE(J41) -> 11 | L41: =H41&":"&K41 -> 7:11 | M41: =VALUE(L41) -> 0.29930556 | N41: Mme Marielle Gracieux, 2015 | O41: 2 | P41: BBR-enregistrement à domicile | Q41: BBR
A42: 42 | B42: =COUNTA(B2:B41) -> 40 | M42: =SUM(M2:M41) -> 11.314583
A43: 43 | B43: 40 | M43: 11.314583 | N43: pour sauvegarde
A44: 44 | B44: 40 | C44: Chiffre obtenu dans digibook | M44: 11.314583 | N44: Chiffre obtenu dans digibook
A45: 45
A46: 46
A47: 47
A48: 48
A49: 49
A50: 50
A51: 51
A52: 52
A53: 53 | B53: 7440A100 | C53: Burri, Julien | D53: Beau à vomir | E53: 2 h. 34 min. | F53: =LEN(E53) -> 12 | G53: =IF(F53=12,LEFT(E53,1),LEFT(E53,2)) -> 2 | H53: =VALUE(G53) -> 2 | I53: =RIGHT(E53,7) -> 34 min. | J53: =LEFT(I53,2) -> 34 | K53: =VALUE(J53) -> 34 | L53: =H53&":"&K53 -> 2:34 | M53: =VALUE(L53) -> 0.10694444 | N53: Mme Maryse Winzenried, 2014 | O53: 1.1 | P53: BBR-studio | Q53: BBR
A54: 54 | B54: 7454A100 | C54: Ernaux, Annie | D54: Regarde les lumières mon amour | E54: 1 h. 43 min. | F54: =LEN(E54) -> 12 | G54: =IF(F54=12,LEFT(E54,1),LEFT(E54,2)) -> 1 | H54: =VALUE(G54) -> 1 | I54: =RIGHT(E54,7) -> 43 min. | J54: =LEFT(I54,2) -> 43 | K54: =VALUE(J54) -> 43 | L54: =H54&":"&K54 -> 1:43 | M54: =VALUE(L54) -> 0.071527778 | N54: Mme Sloane Kersusan, 2015 | O54: 2 | P54: BBR-studio | Q54: BBR
A55: 55 | B55: 7509A100 | C55: Marquis, Sarah | D55: Sauvage par nature : 3 ans de marche extrême en solitaire de Sibérie en Australie | E55: 8 h. 20 min. | F55: =LEN(E55) -> 12 | G55: =IF(F55=12,LEFT(E55,1),LEFT(E55,2)) -> 8 | H55: =VALUE(G55) -> 8 | I55: =RIGHT(E55,7) -> 20 min. | J55: =LEFT(I55,2) -> 20 | K55: =VALUE(J55) -> 20 | L55: =H55&":"&K55 -> 8:20 | M55: =VALUE(L55) -> 0.34722222 | N55: Mme Viviane Gonzalez, 2014 | O55: 5 | P55: BBR-studio | Q55: BBR
A56: 56 | B56: 7511A100 | C56: Halter, Marek | D56: L'inconnue de Birobidjan | E56: 13 h. 34 min. | F56: =LEN(E56) -> 13 | G56: =IF(F56=12,LEFT(E56,1),LEFT(E56,2)) -> 13 | H56: =VALUE(G56) -> 13 | I56: =RIGHT(E56,7) -> 34 min. | J56: =LEFT(I56,2) -> 34 | K56: =VALUE(J56) -> 34 | L56: =H56&":"&K56 -> 13:34 | M56: =VALUE(L56) -> 0.56527778 | N56: Mme Michèle Roullet, 2014 | O56: 1.1 | P56: BBR-studio | Q56: BBR
A57: 57 | B57: 7512A100 | C57: Leon, Donna | D57: [Une enquête du commissaire Brunetti] : L'inconnu du Grand Canal | E57: 9 h. 59 min. | F57: =LEN(E57) -> 12 | G57: =IF(F57=12,LEFT(E57,1),LEFT(E57,2)) -> 9 | H57: =VALUE(G57) -> 9 | I57: =RIGHT(E57,7) -> 59 min. | J57: =LEFT(I57,2) -> 59 | K57: =VALUE(J57) -> 59 | L57: =H57&":"&K57 -> 9:59 | M57: =VALUE(L57) -> 0.41597222 | N57: Mme Anne Fauche, 2014 | O57: 1.2 | P57: BBR-studio | Q57: BBR
A58: 58 | B58: 7514A100 | C58: Decorvet, Anne-Claire | D58: L'instant limite : nouvelles | E58: 6 h. 06 min. | F58: =LEN(E58) -> 12 | G58: =IF(F58=12,LEFT(E58,1),LEFT(E58,2)) -> 6 | H58: =VALUE(G58) -> 6 | I58: =RIGHT(E58,7) -> 06 min. | J58: =LEFT(I58,2) -> 06 | K58: =VALUE(J58) -> 6 | L58: =H58&":"&K58 -> 6:6 | M58: =VALUE(L58) -> 0.25416667 | N58: Mme Monique Baré, M. Olivier Annen, 2014 | O58: 1.8 | P58: BBR-studio | Q58: BBR
A59: 59 | B59: 7516A100 | C59: Safier, David | D59: Sors de ce corps, William ! : roman | E59: 8 h. 43 min. | F59: =LEN(E59) -> 12 | G59: =IF(F59=12,LEFT(E59,1),LEFT(E59,2)) -> 8 | H59: =VALUE(G59) -> 8 | I59: =RIGHT(E59,7) -> 43 min. | J59: =LEFT(I59,2) -> 43 | K59: =VALUE(J59) -> 43 | L59: =H59&":"&K59 -> 8:43 | M59: =VALUE(L59) -> 0.36319444 | N59: Mme Mélanie Refine, 2015 | O59: 1.15 | P59: BBR-studio | Q59: BBR
A60: 60 | B60: 7517A100 | C60: Tanizaki, Jun'ichiro | D60: Le secret et autres textes | E60: 4 h. 29 min. | F60: =LEN(E60) -> 12 | G60: =IF(F60=12,LEFT(E60,1),LEFT(E60,2)) -> 4 | H60: =VALUE(G60) -> 4 | I60: =RIGHT(E60,7) -> 29 min. | J60: =LEFT(I60,2) -> 29 | K60: =VALUE(J60) -> 29 | L60: =H60&":"&K60 -> 4:29 | M60: =VALUE(L60) -> 0.18680556 | N60: Mme Christine Escurriola, 2015 | O60: 1.8 | P60: BBR-studio | Q60: BBR
A61: 61 | B61: 7518A100 | C61: Casadesus, Gisèle | D61: 100 ans, c'est passé si vite | E61: 6 h. 05 min. | F61: =LEN(E61) -> 12 | G61: =IF(F61=12,LEFT(E61,1),LEFT(E61,2)) -> 6 | H61: =VALUE(G61) -> 6 | I61: =RIGHT(E61,7) -> 05 min. | J61: =LEFT(I61,2) -> 05 | K61: =VALUE(J61) -> 5 | L61: =H61&":"&K61 -> 6:5 | M61: =VALUE(L61) -> 0.25347222 | N61: Mme Anne-Marie Scaramuzzi, 2015 | O61: 3 | P61: BBR-studio | Q61: BBR
A62: 62 | B62: 7519A100 | C62: Lévi-Strauss, Monique | D62: Une enfance dans la gueule du loup | E62: 3 h. 57 min. | F62: =LEN(E62) -> 12 | G62: =IF(F62=12,LEFT(E62,1),LEFT(E62,2)) -> 3 | H62: =VALUE(G62) -> 3 | I62: =RIGHT(E62,7) -> 57 min. | J62: =LEFT(I62,2) -> 57 | K62: =VALUE(J62) -> 57 | L62: =H62&":"&K62 -> 3:57 | M62: =VALUE(L62) -> 0.16458333 | N62: Mme Martine Tavelli, 2015 | O62: 2 | P62: BBR-studio | Q62: BBR
A63: 63 | B63: 7520A100 | C63: Leon, Donna | D63: [Une enquête du commissaire Brunetti] : Deux veuves pour un testament | E63: 8 h. 42 min. | F63: =LEN(E63) -> 12 | G63: =IF(F63=12,LEFT(E63,1),LEFT(E63,2)) -> 8 | H63: =VALUE(G63) -> 8 | I63: =RIGHT(E63,7) -> 42 min. | J63: =LEFT(I63,2) -> 42 | K63: =VALUE(J63) -> 42 | L63: =H63&":"&K63 -> 8:42 | M63: =VALUE(L63) -> 0.3625 | N63: Mme Béatrice Schrenzel, 2015 | O63: 1.2 | P63: BBR-studio | Q63: BBR
A64: 64 | B64: 7521A100 | C64: Cartland, Barbara | D64: Un duc à vendre | E64: 6 h. 44 min. | F64: =LEN(E64) -> 12 | G64: =IF(F64=12,LEFT(E64,1),LEFT(E64,2)) -> 6 | H64: =VALUE(G64) -> 6 | I64: =RIGHT(E64,7) -> 44 min. | J64: =LEFT(I64,2) -> 44 | K64: =VALUE(J64) -> 44 | L64: =H64&":"&K64 -> 6:44 | M64: =VALUE(L64) -> 0.28055556 | N64: Mme Arabelle Viñolo Kotzinian, 2015 | O64: 1.11 | P64: BBR-studio | Q64: BBR
... A110: 110 | B110: 7644A100 | C110: Lahens, Yanick | D110: Bain de lune : roman | E110: 6 h. 36 min. | F110: =LEN(E110) -> 12 | G110: =IF(F110=12,LEFT(E110,1),LEFT(E110,2)) -> 6 | H110: =VALUE(G110) -> 6 | I110: =RIGHT(E110,7) -> 36 min. | J110: =LEFT(I110,2) -> 36 | K110: =VALUE(J110) -> 36 | L110: =H110&":"&K110 -> 6:36 | M110: =VALUE(L110) -> 0.275 | N110: Mme Béatrice Schrenzel, 2015 | O110: 1.1 | P110: BBR-studio | Q110: BBR
A111: 111 | B111: 7646A100 | D111: Le groupe créatif et littéraire du Foyer du Vallon | E111: 2 h. 21 min. | F111: =LEN(E111) -> 12 | G111: =IF(F111=12,LEFT(E111,1),LEFT(E111,2)) -> 2 | H111: =VALUE(G111) -> 2 | I111: =RIGHT(E111,7) -> 21 min. | J111: =LEFT(I111,2) -> 21 | K111: =VALUE(J111) -> 21 | L111: =H111&":"&K111 -> 2:21 | M111: =VALUE(L111) -> 0.097916667 | N111: Mmes Laurence Drécourt, Muriel Mérat, M. Philippe Koller, 2015 | O111: 2 | P111: BBR-studio | Q111: BBR
A112: 112 | B112: 7647A100 | C112: Dupuy, Aline | D112: Journal d'une lycéenne sous l'Occupation : Toulouse 1943-1945 | E112: 16 h. 42 min. | F112: =LEN(E112) -> 13 | G112: =IF(F112=12,LEFT(E112,1),LEFT(E112,2)) -> 16 | H112: =VALUE(G112) -> 16 | I112: =RIGHT(E112,7) -> 42 min. | J112: =LEFT(I112,2) -> 42 | K112: =VALUE(J112) -> 42 | L112: =H112&":"&K112 -> 16:42 | M112: =VALUE(L112) -> 0.69583333 | N112: Mme Magnolia Papastratis, 2015 | O112: 7.5 | P112: BBR-studio | Q112: BBR
A113: 113 | B113: 7649A100 | C113: Baricco, Alessandro | D113: Les barbares : essai sur la mutation | E113: 6 h. 24 min. | F113: =LEN(E113) -> 12 | G113: =IF(F113=12,LEFT(E113,1),LEFT(E113,2)) -> 6 | H113: =VALUE(G113) -> 6 | I113: =RIGHT(E113,7) -> 24 min. | J113: =LEFT(I113,2) -> 24 | K113: =VALUE(J113) -> 24 | L113: =H113&":"&K113 -> 6:24 | M113: =VALUE(L113) -> 0.26666667 | N113: M. Louis Martinet, 2015 | O113: 7.1 | P113: BBR-studio | Q113: BBR
A114: 114 | B114: 7650A100 | C114: Fitzgerald, Francis Scott | D114: Bernice se coiffe à la garçonne ; précédé de Le pirate de la côte | E114: 2 h. 59 min. | F114: =LEN(E114) -> 12 | G114: =IF(F114=12,LEFT(E114,1),LEFT(E114,2)) -> 2 | H114: =VALUE(G114) -> 2 | I114: =RIGHT(E114,7) -> 59 min. | J114: =LEFT(I114,2) -> 59 | K114: =VALUE(J114) -> 59 | L114: =H114&":"&K114 -> 2:59 | M114: =VALUE(L114) -> 0.12430556 | N114: Mme Rose-Marie Fuchs Nicolas, 2015 | O114: 1.8 | P114: BBR-studio | Q114: BBR
A115: 115 | B115: 7651A100 | C115: Marin, Agnès | D115: L'alouette | E115: 00 h. 44 min. | F115: =LEN(E115) -> 13 | G115: =IF(F115=12,LEFT(E115,1),LEFT(E115,2)) -> 00 | H115: =VALUE(G115) -> 0 | I115: =RIGHT(E115,7) -> 44 min. | J115: =LEFT(I115,2) -> 44 | K115: =VALUE(J115) -> 44 | L115: =H115&":"&K115 -> 0:44 | M115: =VALUE(L115) -> 0.030555556 | N115: Mme Arlette Bratschi, 2015 | O115: 6.3 | P115: BBR-studio | Q115: BBR
A116: 116 | B116: 7652A100 | C116: Déon, Michel | D116: "Je vous écris d'Italie..." | E116: 11 h. 04 min. | F116: =LEN(E116) -> 13 | G116: =IF(F116=12,LEFT(E116,1),LEFT(E116,2)) -> 11 | H116: =VALUE(G116) -> 11 | I116: =RIGHT(E116,7) -> 04 min. | J116: =LEFT(I116,2) -> 04 | K116: =VALUE(J116) -> 4 | L116: =H116&":"&K116 -> 11:4 | M116: =VALUE(L116) -> 0.46111111 | N116: Mme Françoise Reversy, 2015 | O116: 1.1 | P116: BBR-studio | Q116: BBR
A117: 117 | B117: 7653A100 | C117: Tabucchi, Antonio | D117: Pour Isabel : un mandala : roman | E117: 3 h. 56 min. | F117: =LEN(E117) -> 12 | G117: =IF(F117=12,LEFT(E117,1),LEFT(E117,2)) -> 3 | H117: =VALUE(G117) -> 3 | I117: =RIGHT(E117,7) -> 56 min. | J117: =LEFT(I117,2) -> 56 | K117: =VALUE(J117) -> 56 | L117: =H117&":"&K117 -> 3:56 | M117: =VALUE(L117) -> 0.16388889 | N117: M. Michel Sangsue, 2015 | O117: 1.1 | P117: BBR-studio | Q117: BBR
A118: 118 | B118: 7654A100 | C118: Rambaud, Patrick | D118: Le maître : roman | E118: 5 h. 27 min. | F118: =LEN(E118) -> 12 | G118: =IF(F118=12,LEFT(E118,1),LEFT(E118,2)) -> 5 | H118: =VALUE(G118) -> 5 | I118: =RIGHT(E118,7) -> 27 min. | J118: =LEFT(I118,2) -> 27 | K118: =VALUE(J118) -> 27 | L118: =H118&":"&K118 -> 5:27 | M118: =VALUE(L118) -> 0.22708333 | N118: M. Denis Allistone, 2015 | O118: 1.12 | P118: BBR-studio | Q118: BBR
A119: 119 | B119: 7655A100 | C119: Palach, Jean-Marie | D119: Souvenirs envolés | E119: 6 h. 12 min. | F119: =LEN(E119) -> 12 | G119: =IF(F119=12,LEFT(E119,1),LEFT(E119,2)) -> 6 | H119: =VALUE(G119) -> 6 | I119: =RIGHT(E119,7) -> 12 min. | J119: =LEFT(I119,2) -> 12 | K119: =VALUE(J119) -> 12 | L119: =H119&":"&K119 -> 6:12 | M119: =VALUE(L119) -> 0.25833333 | N119: Mme Anne Fauche, 2015 | O119: 1.2 | P119: BBR-studio | Q119: BBR
A120: 120 | B120: 7657A100 | C120: Montaldi, Valeria | D120: La prisonnière de Venise : roman | E120: 12 h. 57 min. | F120: =LEN(E120) -> 13 | G120: =IF(F120=12,LEFT(E120,1),LEFT(E120,2)) -> 12 | H120: =VALUE(G120) -> 12 | I120: =RIGHT(E120,7) -> 57 min. | J120: =LEFT(I120,2) -> 57 | K120: =VALUE(J120) -> 57 | L120: =H120&":"&K120 -> 12:57 | M120: =VALUE(L120) -> 0.53958333 | N120: Mme Anne Fauche, 2015 | O120: 1.12 | P120: BBR-studio | Q120: BBR
A121: 121 | B121: 7658A100 | C121: Malroux, Antonin | D121: La cascade des loups | E121: 8 h. 35 min. | F121: =LEN(E121) -> 12 | G121: =IF(F121=12,LEFT(E121,1),LEFT(E121,2)) -> 8 | H121: =VALUE(G121) -> 8 | I121: =RIGHT(E121,7) -> 35 min. | J121: =LEFT(I121,2) -> 35 | K121: =VALUE(J121) -> 35 | L121: =H121&":"&K121 -> 8:35 | M121: =VALUE(L121) -> 0.35763889 | N121: Mme Anne Battiaz-Laubreaux, 2015 | O121: 1.13 | P121: BBR-studio | Q121: BBR
A122: 122 | B122: 7659A100 | C122: Abd al Malik | D122: Place de la République : pour une spiritualité laïque | E122: 00 h. 38 min. | F122: =LEN(E122) -> 13 | G122: =IF(F122=12,LEFT(E122,1),LEFT(E122,2)) -> 00 | H122: =VALUE(G122) -> 0 | I122: =RIGHT(E122,7) -> 38 min. | J122: =LEFT(I122,2) -> 38 | K122: =VALUE(J122) -> 38 | L122: =H122&":"&K122 -> 0:38 | M122: =VALUE(L122) -> 0.026388889 | N122: M. Philippe Koller, 2015 | O122: 7.1 | P122: BBR-studio | Q122: BBR
A123: 123 | B123: 7660A100 | C123: Starobinski, Jean | D123: Notre seul, notre unique jardin | E123: 00 h. 59 min. | F123: =LEN(E123) -> 13 | G123: =IF(F123=12,LEFT(E123,1),LEFT(E123,2)) -> 00 | H123: =VALUE(G123) -> 0 | I123: =RIGHT(E123,7) -> 59 min. | J123: =LEFT(I123,2) -> 59 | K123: =VALUE(J123) -> 59 | L123: =H123&":"&K123 -> 0:59 | M123: =VALUE(L123) -> 0.040972222 | N123: M. Michel Sangsue, 2015 | O123: 7.1 | P123: BBR-studio | Q123: BBR
... A208: 208 | B208: 7914A100 | C208: Hardy, Françoise | D208: Avis non autorisés... | E208: 7 h. 22 min. | F208: =LEN(E208) -> 12 | G208: =IF(F208=12,LEFT(E208,1),LEFT(E208,2)) -> 7 | H208: =VALUE(G208) -> 7 | I208: =RIGHT(E208,7) -> 22 min. | J208: =LEFT(I208,2) -> 22 | K208: =VALUE(J208) -> 22 | L208: =H208&":"&K208 -> 7:22 | M208: =VALUE(L208) -> 0.30694444 | N208: Mme Martine Tavelli, 2015 | O208: 7.5 | P208: BBR-studio | Q208: BBR
A209: 209 | B209: 7915A100 | D209: Pourquoi l'eau de mer est salée : et autres contes de Corée | E209: 1 h. 57 min. | F209: =LEN(E209) -> 12 | G209: =IF(F209=12,LEFT(E209,1),LEFT(E209,2)) -> 1 | H209: =VALUE(G209) -> 1 | I209: =RIGHT(E209,7) -> 57 min. | J209: =LEFT(I209,2) -> 57 | K209: =VALUE(J209) -> 57 | L209: =H209&":"&K209 -> 1:57 | M209: =VALUE(L209) -> 0.08125 | N209: Mme Laurence Bovay, 2015 | O209: 6.1 | P209: BBR-studio | Q209: BBR
A210: 210 | B210: 7916A100 | C210: Haerri, Silvia | D210: Nouaison | E210: 1 h. 06 min. | F210: =LEN(E210) -> 12 | G210: =IF(F210=12,LEFT(E210,1),LEFT(E210,2)) -> 1 | H210: =VALUE(G210) -> 1 | I210: =RIGHT(E210,7) -> 06 min. | J210: =LEFT(I210,2) -> 06 | K210: =VALUE(J210) -> 6 | L210: =H210&":"&K210 -> 1:6 | M210: =VALUE(L210) -> 0.045833333 | N210: Mme Martine Brandt, 2015 | O210: 2 | P210: BBR-studio | Q210: BBR
A211: 211 | B211: 7917A100 | C211: Ferrier, Ariane | D211: Fragile | E211: 3 h. 38 min. | F211: =LEN(E211) -> 12 | G211: =IF(F211=12,LEFT(E211,1),LEFT(E211,2)) -> 3 | H211: =VALUE(G211) -> 3 | I211: =RIGHT(E211,7) -> 38 min. | J211: =LEFT(I211,2) -> 38 | K211: =VALUE(J211) -> 38 | L211: =H211&":"&K211 -> 3:38 | M211: =VALUE(L211) -> 0.15138889 | N211: Mme Mélanie Refine, 2015 | O211: 7.1 | P211: BBR-studio | Q211: BBR
A212: 212 | B212: 7918A100 | C212: Clerc, Gaston | D212: Le secret de la porte de fer | E212: 7 h. 06 min. | F212: =LEN(E212) -> 13 | G212: =IF(F212=12,LEFT(E212,1),LEFT(E212,2)) -> 7 | H212: =VALUE(G212) -> 7 | I212: =RIGHT(E212,7) -> 06 min. | J212: =LEFT(I212,2) -> 06 | K212: =VALUE(J212) -> 6 | L212: =H212&":"&K212 -> 7:6 | M212: =VALUE(L212) -> 0.29583333 | N212: Mme Arlette Bratschi, 2015 | O212: 1.99 | P212: BBR-studio | Q212: BBR
A213: 213 | B213: 7919A100 | C213: Markaris, Petros | D213: [Une enquête de Kostas Charitos] : [2] : Le justicier d’Athènes | E213: 8 h. 52 min. | F213: =LEN(E213) -> 12 | G213: =IF(F213=12,LEFT(E213,1),LEFT(E213,2)) -> 8 | H213: =VALUE(G213) -> 8 | I213: =RIGHT(E213,7) -> 52 min. | J213: =LEFT(I213,2) -> 52 | K213: =VALUE(J213) -> 52 | L213: =H213&":"&K213 -> 8:52 | M213: =VALUE(L213) -> 0.36944444 | N213: M. Albert Morard, 2015 | O213: 1.2 | P213: BBR-studio | Q213: BBR
A214: 214 | B214: 7921A100 | C214: Gilliard, Valérie | D214: Le canal : roman | E214: 2 h. 47 min. | F214: =LEN(E214) -> 12 | G214: =IF(F214=12,LEFT(E214,1),LEFT(E214,2)) -> 2 | H214: =VALUE(G214) -> 2 | I214: =RIGHT(E214,7) -> 47 min. | J214: =LEFT(I214,2) -> 47 | K214: =VALUE(J214) -> 47 | L214: =H214&":"&K214 -> 2:47 | M214: =VALUE(L214) -> 0.11597222 | N214: Lecteurs multiples, 2015 | O214: 1.1 | P214: BBR-studio | Q214: BBR
A215: 215 | B215: 7922A100 | C215: Dubois, Géraldine | D215: Dehors la vieille ! | E215: 7 h. 41 min. | F215: =LEN(E215) -> 12 | G215: =IF(F215=12,LEFT(E215,1),LEFT(E215,2)) -> 7 | H215: =VALUE(G215) -> 7 | I215: =RIGHT(E215,7) -> 41 min. | J215: =LEFT(I215,2) -> 41 | K215: =VALUE(J215) -> 41 | L215: =H215&":"&K215 -> 7:41 | M215: =VALUE(L215) -> 0.32013889 | N215: M. Zino Davidoff, 2015 | O215: 8 | P215: BBR-studio | Q215: BBR
A216: 216 | B216: 7923A100 | C216: Récondo, Léonor de | D216: Amours : roman | E216: 3 h. 51 min. | F216: =LEN(E216) -> 12 | G216: =IF(F216=12,LEFT(E216,1),LEFT(E216,2)) -> 3 | H216: =VALUE(G216) -> 3 | I216: =RIGHT(E216,7) -> 51 min. | J216: =LEFT(I216,2) -> 51 | K216: =VALUE(J216) -> 51 | L216: =H216&":"&K216 -> 3:51 | M216: =VALUE(L216) -> 0.16041667 | N216: Mme Carole Extermann, 2015 | O216: 1.1 | P216: BBR-studio | Q216: BBR
A217: 217 | B217: 7924A100 | C217: Lévy, Justine | D217: La gaieté : roman | E217: 4 h. 58 min. | F217: =LEN(E217) -> 12 | G217: =IF(F217=12,LEFT(E217,1),LEFT(E217,2)) -> 4 | H217: =VALUE(G217) -> 4 | I217: =RIGHT(E217,7) -> 58 min. | J217: =LEFT(I217,2) -> 58 | K217: =VALUE(J217) -> 58 | L217: =H217&":"&K217 -> 4:58 | M217: =VALUE(L217) -> 0.20694444 | N217: Mme Laurence Bovay, 2015 | O217: 1.1 | P217: BBR-studio | Q217: BBR
A218: 218 | B218: 7926A100 | C218: Menna, Antonio | D218: L'étrange histoire de l'ours brun abattu dans les quartiers espagnols de Naples | E218: 5 h. 20 min. | F218: =LEN(E218) -> 12 | G218: =IF(F218=12,LEFT(E218,1),LEFT(E218,2)) -> 5 | H218: =VALUE(G218) -> 5 | I218: =RIGHT(E218,7) -> 20 min. | J218: =LEFT(I218,2) -> 20 | K218: =VALUE(J218) -> 20 | L218: =H218&":"&K218 -> 5:20 | M218: =VALUE(L218) -> 0.22222222 | N218: M. Quentin Bohlen, 2015 | O218: 1.1 | P218: BBR-studio | Q218: BBR
A219: 219 | B219: 7927A100 | C219: Jónasson, Jon Atli | D219: Les enfants de Dimmavick : novella | E219: 1 h. 36 min. | F219: =LEN(E219) -> 12 | G219: =IF(F219=12,LEFT(E219,1),LEFT(E219,2)) -> 1 | H219: =VALUE(G219) -> 1 | I219: =RIGHT(E219,7) -> 36 min. | J219: =LEFT(I219,2) -> 36 | K219: =VALUE(J219) -> 36 | L219: =H219&":"&K219 -> 1:36 | M219: =VALUE(L219) -> 0.066666667 | N219: Mme Pauline Rappaz, 2015 | O219: 1.12 | P219: BBR-studio | Q219: BBR
A220: 220 | B220: 7928A100 | C220: Baronsky, Eva | D220: Monsieur Mozart se réveille | E220: 11 h. 07 min. | F220: =LEN(E220) -> 13 | G220: =IF(F220=12,LEFT(E220,1),LEFT(E220,2)) -> 11 | H220: =VALUE(G220) -> 11 | I220: =RIGHT(E220,7) -> 07 min. | J220: =LEFT(I220,2) -> 07 | K220: =VALUE(J220) -> 7 | L220: =H220&":"&K220 -> 11:7 | M220: =VALUE(L220) -> 0.46319444 | N220: Mme Viviane Gonzalez, 2015 | O220: 1.1 | P220: BBR-studio | Q220: BBR
A221: 221 | B221: 7929A100 | C221: Cossery, Albert | D221: Les hommes oubliés de Dieu | E221: 3 h. 41 min. | F221: =LEN(E221) -> 12 | G221: =IF(F221=12,LEFT(E221,1),LEFT(E221,2)) -> 3 | H221: =VALUE(G221) -> 3 | I221: =RIGHT(E221,7) -> 41 min. | J221: =LEFT(I221,2) -> 41 | K221: =VALUE(J221) -> 41 | L221: =H221&":"&K221 -> 3:41 | M221: =VALUE(L221) -> 0.15347222 | N221: M. Louis Martinet, 2015 | O221: 1.8 | P221: BBR-studio | Q221: BBR
... A258: 258 | B258: 8056A100 | C258: Roche, Florence | D258: La terre des Falgères : roman | E258: 10 h. 34 min. | F258: =LEN(E258) -> 13 | G258: =IF(F258=12,LEFT(E258,1),LEFT(E258,2)) -> 10 | H258: =VALUE(G258) -> 10 | I258: =RIGHT(E258,7) -> 34 min. | J258: =LEFT(I258,2) -> 34 | K258: =VALUE(J258) -> 34 | L258: =H258&":"&K258 -> 10:34 | M258: =VALUE(L258) -> 0.44027778 | N258: Mme Anne-Marie Scaramuzzi, 2015 | O258: 1.13 | P258: BBR-studio | Q258: BBR
A259: 259 | B259: =COUNTA(B53:B258) -> 206 | M259: =SUM(M53:M258) -> 59.990278
A260: 260 | B260: 206 | M260: 59.990278 | N260: pour sauvegarde
A261: 261 | B261: 206 | C261: Chiffre obtenu dans digibook | M261: 59.990278 | N261: Chiffre obtenu dans digibook
A262: 262
A263: 263 | B263: =B259+B42 -> 246 | C263: total studios + domicile | M263: =M259+M42 -> 71.304861 | N263: total studios + domicile
A264: 264
A265: 265
A266: 266
A267: 267
A268: 268
A269: 269 | B269: 7026A100 | C269: Souvestre, Pierre | D269: Fantômas : Le train perdu | E269: 12 h. 48 min. | F269: =LEN(E269) -> 13 | G269: =IF(F269=12,LEFT(E269,1),LEFT(E269,2)) -> 12 | H269: =VALUE(G269) -> 12 | I269: =RIGHT(E269,7) -> 48 min. | J269: =LEFT(I269,2) -> 48 | K269: =VALUE(J269) -> 48 | L269: =H269&":"&K269 -> 12:48 | M269: =VALUE(L269) -> 0.53333333 | N269: Jean Barney | O269: 1.2 | P269: Audio commerce | Q269: BBR
A270: 270 | B270: 7037A100 | C270: Souvestre, Pierre | D270: Fantômas : Le jockey masqué | E270: 13 h. 22 min. | F270: =LEN(E270) -> 13 | G270: =IF(F270=12,LEFT(E270,1),LEFT(E270,2)) -> 13 | H270: =VALUE(G270) -> 13 | I270: =RIGHT(E270,7) -> 22 min. | J270: =LEFT(I270,2) -> 22 | K270: =VALUE(J270) -> 22 | L270: =H270&":"&K270 -> 13:22 | M270: =VALUE(L270) -> 0.55694444 | N270: Michel Raimbault | O270: 1.2 | P270: Audio commerce | Q270: BBR
A271: 271 | B271: 7162A100 | C271: Gélinet, Patrice | D271: La guerre d'Algérie | E271: 10 h. 57 min. | F271: =LEN(E271) -> 13 | G271: =IF(F271=12,LEFT(E271,1),LEFT(E271,2)) -> 10 | H271: =VALUE(G271) -> 10 | I271: =RIGHT(E271,7) -> 57 min. | J271: =LEFT(I271,2) -> 57 | K271: =VALUE(J271) -> 57 | L271: =H271&":"&K271 -> 10:57 | M271: =VALUE(L271) -> 0.45625 | N271: Lecteurs multiples | O271: 9.93 | P271: Audio commerce | Q271: BBR
A272: 272 | B272: 7188A100 | C272: Terzieff, Laurent | D272: Du visible à l'invisible | E272: 2 h. 34 min. | F272: =LEN(E272) -> 12 | G272: =IF(F272=12,LEFT(E272,1),LEFT(E272,2)) -> 2 | H272: =VALUE(G272) -> 2 | I272: =RIGHT(E272,7) -> 34 min. | J272: =LEFT(I272,2) -> 34 | K272: =VALUE(J272) -> 34 | L272: =H272&":"&K272 -> 2:34 | M272: =VALUE(L272) -> 0.10694444 | N272: Laurent Terzieff | O272: 7.1 | P272: Audio commerce | Q272: BBR
...

Sheet Audio par type de média2
A1: No d'exemplaire | B1: Auteur | C1: Titre | D1: Type de média 2
A2: 7521A100 | B2: Cartland, Barbara | C2: Un duc à vendre | D2: A
A3: 7933A100 | B3: Roberts, Nora | C3: Les ombres du lac | D3: A
A4: 7575A100 | B4: Atangana, Louis | C4: Bille H. | D4: B
A5: 7996A100 | B5: Benzoni, Juliette | C5: Reines tragiques | D5: B
A6: 7595A100 | B6: Bon, François | C6: Rock'n roll : un portrait de Led Zeppelin | D6: B
A7: 7696A100 | B7: Calvet, Louis-Jean | C7: Georges Moustaki : une vie | D7: B
A8: 7518A100 | B8: Casadesus, Gisèle | C8: 100 ans, c'est passé si vite | D8: B
A9: 7697A100 | B9: Crick, Bernard R. | C9: George Orwell | D9: B
A10: 7793A100 | B10: Delaye, Fabrice | C10: Patrick Aebischer | D10: B
A11: 7662A100 | B11: Étèvenaux, Jean | C11: Napoléon III : visionnaire de son temps | D11: B
A12: 7847A100 | B12: Gallo, Max | C12: Machiavel et Savonarole : la glace et le feu | D12: B
... A23: 7838A100 | B23: Skloot, Rebecca | C23: La vie immortelle d'Henrietta Lacks | D23: B
A24: 7709A100 | C24: La tortue d'Eschyle et autres morts stupides de l'histoire | D24: D
A25: 8012A100 | B25: Aillagon, Jean-Jacques | C25: Versailles en 50 dates | D25: D
A26: 8028A100 | B26: Antonetti, Pierre | C26: Histoire de Florence | D26: D
A27: 7524A100 | B27: Arnaud, Claude | C27: Proust contre Cocteau | D27: D
A28: 7813A100 | B28: Autissier, Isabelle | C28: Passer par le Nord : la nouvelle route maritime | D28: D
A29: 7749A100 | B29: Baldin, Damien | C29: Histoire des animaux domestiques : XIXe-XXe siècle | D29: D
A30: 7685A100 | B30: Baraton, Alain | C30: Vice et Versailles : crimes, trahisons et autres empoisonnements au palais du Roi-Soleil | D30: D
A31: 7748A100 | B31: Baudet, Jean | C31: Histoire de la cuisine : une philosophie du goût | D31: D
A32: 7999A100 | B32: Berberova, Nina | C32: L'affaire Kravtchenko | D32: D
A33: 8013A100 | B33: Bern, Stéphane | C33: Les pourquoi de l'Histoire | D33: D
A34: 7547A100 | B34: Braden, Gregg | C34: Secrets de l'art perdu de la prière | D34: D
A35: 7720A100 | B35: Braunstein, Florence | C35: La culture générale pour les nuls | D35: D
A36: 7664A100 | B36: Cadieux, Axel | C36: Une série de tueurs : les serial killers qui ont inspiré le cinéma | D36: D
... A95: 7545A100 | B95: Wozniak, Éric | C95: La rythmologie | D95: D
A96: 7645A100 | C96: Philippe Favre : pressé de vivre : ses amis témoignent | D96: E
A97: 7659A100 | B97: Abd al Malik | C97: Place de la République : pour une spiritualité laïque | D97: E
A98: 7817A100 | B98: Alassane, Anne | C98: Pour l'amour des miens : témoignage | D98: E
A99: 7568A100 | B99: Alyn, Marc | C99: Monsieur le Chat : promenades littéraires | D99: E
A100: 7633A100 | B100: Attali, Jacques | C100: Devenir soi : prenez le pouvoir sur votre vie ! | D100: E
A101: 7649A100 | B101: Baricco, Alessandro | C101: Les barbares : essai sur la mutation | D101: E
A102: 8045A100 | B102: Bly, Nelly | C102: 10 jours dans un asile | D102: E
A103: 7818A100 | B103: Chauvin, Ingrid | C103: A coeur ouvert | D103: E
A104: 7913A100 | B104: Chollet, Mona | C104: La tyrannie de la réalité | D104: E
A105: 7758A100 | B105: Cochard, Zara | C105: Patience enragée : apprendre avec un handicap | D105: E
A106: 7909A100 | B106: Cochard, Zara | C106: Choisir la vie | D106: E
A107: 7551A100 | B107: Delacomptée, Emmanuelle | C107: Molière à la campagne | D107: E
A108: 7785A100 | B108: Delpech, Michel | C108: Vivre ! | D108: E
... A145: 8011A100 | B145: Thomas, Chantal | C145: L'échange des princesses | D145: H
A146: 7915A100 | C146: Pourquoi l'eau de mer est salée : et autres contes de Corée | D146: L
A147: 7613A100 | B147: Allais, Alphonse | C147: Le langage des fleurs ; Savoir hennir ; Le Chambardoscope | D147: L
A148: 7845A100 | B148: Caputo, Nata | C148: Letiko, la fille du soleil : conte grec | D148: L
A149: 7679A100 | B149: Demers, Dominique | C149: Annabel et la bête | D149: L
A150: 7971A100 | B150: Saint-Exupéry, Antoine de | C150: Le petit prince | D150: L
A151: 7616A100 | B151: Supervielle, Jules | C151: Le boeuf et l'âne de la crèche | D151: L
A152: 7892A100 | C152: Genève sang dessus dessous : 5 fictions policières | D152: N
A153: 7525A100 | B153: Aymé, Marcel | C153: La bonne peinture | D153: N
A154: 7440A100 | B154: Burri, Julien | C154: Beau à vomir | D154: N
A155: 7895A100 | B155: Cervantes Saavedra, Miguel de | C155: La petite gitane | D155: N
A156: 7929A100 | B156: Cossery, Albert | C156: Les hommes oubliés de Dieu | D156: N
A157: 7514A100 | B157: Decorvet, Anne-Claire | C157: L'instant limite : nouvelles | D157: N
A158: 8048A100 | B158: Delerm, Philippe | C158: Les eaux troubles du mojito : et autres belles raisons d'habiter sur terre | D158: N
A159: 7881A100 | B159: Echenoz, Jean | C159: Caprice de la reine | D159: N
A160: 7650A100 | B160: Fitzgerald, Francis Scott | C160: Bernice se coiffe à la garçonne ; précédé de Le pirate de la côte | D160: N
A161: 7676A100 | B161: Gallant, Mavis | C161: Week-end en Bourgogne | D161: N
A162: 7614A100 | B162: Gavalda, Anna | C162: La vie en mieux : deux histoires | D162: N
A163: 7675A100 | B163: Hemingway, Ernest | C163: Une drôle de traversée | D163: N
A164: 7804A100 | B164: Méril, Macha | C164: L'amour dans tous ses états | D164: N
... A491: 8056A100 | B491: Roche, Florence | C491: La terre des Falgères : roman | D491: RT
A492: 7646A100 | C492: Le groupe créatif et littéraire du Foyer du Vallon | D492: S
A493: 7931A100 | B493: Arthaud, Florence | C493: Cette nuit, la mer est noire | D493: S
A494: 7870A100 | B494: Bernard, Céline | C494: Jean-Claude Perronnet : l'homme qui court avec les yeux des autres | D494: S
A495: 7956A100 | B495: Bobin, Christian | C495: Noireclaire | D495: S
A496: 7711A100 | B496: Chancel, Jacques | C496: La nuit attendra | D496: S
A497: 7689A100 | B497: Davant, Sophie | C497: Ce que j'ai appris de moi : journal d'une quinqua | D497: S
A498: 7800A100 | B498: Demoulin-Astre, Marie-Jo | C498: Le nid vide | D498: S
A499: 7454A100 | B499: Ernaux, Annie | C499: Regarde les lumières mon amour | D499: S
A500: 7546A100 | B500: Frain, Irène | C500: Sorti de rien : récit | D500: S
A501: 7780A100 | B501: Giannoni, Chantal | C501: Encorselée : récit | D501: S
A502: 7916A100 | B502: Haerri, Silvia | C502: Nouaison | D502: S
A503: 7593A100 | B503: Hulot, Nicolas | C503: États d'âme | D503: S
A504: 7534A100 | B504: Kerangal, Maylis de | C504: A ce stade de la nuit | D504: S
... A538: 7984A100 | B538: Teulé, Jean | C538: Héloïse, ouille ! ; suivi d'un entretien entre J. Teulé et D. Pinon | D538: X
A539: =COUNTA(D2:D538) -> 537 | B539: Total des ouvrages
A540: =A539-A541-A542 -> 433 | B540: Fictions
A541: =COUNTIF(D2:D538,"E") -> 32 | B541: Littératures diverses
A542: =COUNTIF(D2:D538,"D") -> 72 | B542: documentaires
A543: =A540+A541+A542 -> 537 | B543: validation

Sheet Heures audio copies
A1: Heures de copies de CD et de titres transférés : | E1: voir dans le fichier | G1: 2015-copies-de-CD+transferts.xlsx

Sheet Heures braille produites
A1: Heures brailles effectuées : | D1: voir dans le fichier | F1: 2015-TRIM.xlsx

Sheet Feuil1
